[
  {
    "Name": "Sener DÜNÜK",
    "Birth Information": "SILVAN - 1978",
    "Organization": "HİZBULLAH Terör Örgütü",
    "Photo URL": "\"/kurumlar/terorarananlar.pol.tr/Arsiv/1625/FotoOrj.jpeg\""
  },
  {
    "Name": "Barbaros KOCAKURT",
    "Birth Information": "IZMIR - 1954",
    "Organization": "FETÖ/PDY Terör Örgütü",
    "Photo URL": "\"/kurumlar/terorarananlar.pol.tr/Arsiv/782/FotoOrj.jpeg\""
  },
  {
    "Name": "Mesut DEMİREL",
    "Birth Information": "ISTANBUL - 1955",
    "Organization": "DHKP/C Terör Örgütü",
    "Photo URL": "\"/kurumlar/terorarananlar.pol.tr/Arsiv/40/FotoOrj.jpeg\""
  },
  {
    "Name": "Filiz DUMAN",
    "Birth Information": "AGRI - 1971",
    "Organization": "PKK/KCK Terör Örgütü",
    "Photo URL": "\"/kurumlar/terorarananlar.pol.tr/Arsiv/111/FotoOrj.jpeg\""
  },
  {
    "Name": "Ömer CİNGÖZ",
    "Birth Information": "İDİL - 1980",
    "Organization": "PKK/KCK Terör Örgütü",
    "Photo URL": "\"/kurumlar/terorarananlar.pol.tr/31KOMISYON/OMER-CINGOZ.jpg\""
  },
  {
    "Name": "Serdar ZİRİĞ",
    "Birth Information": "İDİL - 1981",
    "Organization": "PKK/KCK Terör Örgütü",
    "Photo URL": "\"/kurumlar/terorarananlar.pol.tr/30-KOMISYON/1_SERDAR-ZIRIG.jpg\""
  },
  {
    "Name": "Mustafa ÖZCAN",
    "Birth Information": "GEDIZ - 1951",
    "Organization": "FETÖ/PDY Terör Örgütü",
    "Photo URL": "\"/kurumlar/terorarananlar.pol.tr/Arsiv/35/FotoOrj.jpeg\""
  },
  {
    "Name": "Yakup Baver KARTAL",
    "Birth Information": "VAN - 1979",
    "Organization": "PKK/KCK Terör Örgütü",
    "Photo URL": "\"/kurumlar/terorarananlar.pol.tr/31KOMISYON/93_YAKUP-BAVER-KARTAL.jpg\""
  },
  {
    "Name": "Ergün ÇAPAN",
    "Birth Information": "ÇİFTELER - 1966",
    "Organization": "FETÖ/PDY Terör Örgütü",
    "Photo URL": "\"/kurumlar/terorarananlar.pol.tr/31KOMISYON/ERGUN-CAPAN.jpg\""
  },
  {
    "Name": "Zübeyir AYDAR",
    "Birth Information": "YANIKSES - 1961",
    "Organization": "PKK/KCK Terör Örgütü",
    "Photo URL": "\"/kurumlar/terorarananlar.pol.tr/Arsiv/19/FotoOrj.jpeg\""
  },
  {
    "Name": "Ahmet ÇAĞLAYAN",
    "Birth Information": "İSPİR - 1968",
    "Organization": "FETÖ/PDY Terör Örgütü",
    "Photo URL": "\"/kurumlar/terorarananlar.pol.tr/31KOMISYON/78_-AHMET-CAGLAYAN.jpg\""
  },
  {
    "Name": "Hüseyin YURDAGÜL",
    "Birth Information": "KAHRAMANMARAŞ - 1972",
    "Organization": "FETÖ/PDY Terör Örgütü",
    "Photo URL": "\"/kurumlar/terorarananlar.pol.tr/31KOMISYON/68HUSEYIN-YURDAGUL.jpg\""
  },
  {
    "Name": "Ferdi ŞEVLİ",
    "Birth Information": "İSTANBUL - 1978",
    "Organization": "PKK/KCK Terör Örgütü",
    "Photo URL": "\"/kurumlar/terorarananlar.pol.tr/31KOMISYON/FERDI-SEVLI.jpg\""
  },
  {
    "Name": "SİNAN SARIGÜL",
    "Birth Information": "TUNCELİ - 1977",
    "Organization": "PKK/KCK Terör Örgütü",
    "Photo URL": "\"/kurumlar/terorarananlar.pol.tr/33KOMISYON/SINAN-SARIGUL.jpg\""
  },
  {
    "Name": "HASAN CEMİLİ/JAMİLİ",
    "Birth Information": "null - null",
    "Organization": "PKK/KCK Terör Örgütü",
    "Photo URL": "\"/kurumlar/terorarananlar.pol.tr/33KOMISYON/HASAN-CEMILI_JAMILI.jpg\""
  },
  {
    "Name": "Mesih GÜLEN",
    "Birth Information": "HASANKALE - 1944",
    "Organization": "FETÖ/PDY Terör Örgütü",
    "Photo URL": "\"/kurumlar/terorarananlar.pol.tr/31KOMISYON/57MESIH-GULEN.jpg\""
  },
  {
    "Name": "Turgay ULU",
    "Birth Information": "ARPAÇAY - 1973",
    "Organization": "MLKP Terör Örgütü",
    "Photo URL": "\"/kurumlar/terorarananlar.pol.tr/Arsiv/141/FotoOrj.jpeg\""
  },
  {
    "Name": "Yusuf Serhat TOPÇU",
    "Birth Information": "VİRANŞEHİR - 1993",
    "Organization": "PKK/KCK Terör Örgütü",
    "Photo URL": "\"/kurumlar/terorarananlar.pol.tr/31KOMISYON/YUSUF-SERHAT-TOPCU.jpg\""
  },
  {
    "Name": "DİLBER İSA",
    "Birth Information": "null - null",
    "Organization": "PKK/KCK Terör Örgütü",
    "Photo URL": "\"/kurumlar/terorarananlar.pol.tr/33KOMISYON/DILBER-ISA.jpg\""
  },
  {
    "Name": "Recep ÖZKAN",
    "Birth Information": "KEŞAN - 1968",
    "Organization": "FETÖ/PDY Terör Örgütü",
    "Photo URL": "\"/kurumlar/terorarananlar.pol.tr/31KOMISYON/75RECEP-OZKAN-.jpg\""
  },
  {
    "Name": "Evrim EVRENSEL",
    "Birth Information": "TORBALI - 1996",
    "Organization": "MLKP Terör Örgütü",
    "Photo URL": "\"/kurumlar/terorarananlar.pol.tr/28-KOMISYON/41_EVRIM-EVRENSEL.jpg\""
  },
  {
    "Name": "Özcan AYTULUNER",
    "Birth Information": "IZMIR - 1967",
    "Organization": "FETÖ/PDY Terör Örgütü",
    "Photo URL": "\"/kurumlar/terorarananlar.pol.tr/Arsiv/1447/FotoOrj.jpeg\""
  },
  {
    "Name": "Sabriye İLGÜN",
    "Birth Information": "PERTEK - 1971",
    "Organization": "PKK/KCK Terör Örgütü",
    "Photo URL": "\"/kurumlar/terorarananlar.pol.tr/Arsiv/332/FotoOrj.jpeg\""
  },
  {
    "Name": "BESİME BAŞAR",
    "Birth Information": "DARENDE - 1979",
    "Organization": "PKK/KCK Terör Örgütü",
    "Photo URL": "\"/kurumlar/terorarananlar.pol.tr/33KOMISYON/BESIME-BASAR.jpg\""
  },
  {
    "Name": "Abdulkadir YILMAZ",
    "Birth Information": "ISKENDERUN - 1967",
    "Organization": "FETÖ/PDY Terör Örgütü",
    "Photo URL": "\"/kurumlar/terorarananlar.pol.tr/Arsiv/337/FotoOrj_1.jpeg\""
  },
  {
    "Name": "Uziya SÜMEYLA",
    "Birth Information": "null - null",
    "Organization": "PKK/KCK Terör Örgütü",
    "Photo URL": "\"/kurumlar/terorarananlar.pol.tr/36_KOMISYON/UZIYA-SUMEYLA.jpg\""
  },
  {
    "Name": "Yusuf COŞKUN",
    "Birth Information": "VARTO/BOYLU - 1983",
    "Organization": "PKK/KCK Terör Örgütü",
    "Photo URL": "\"/kurumlar/terorarananlar.pol.tr/Arsiv/1152/FotoOrj.jpeg\""
  },
  {
    "Name": "Nalan ORAL",
    "Birth Information": "KARTAL - 1979",
    "Organization": "DHKP/C Terör Örgütü",
    "Photo URL": "\"/kurumlar/terorarananlar.pol.tr/Arsiv/368/FotoOrj_1.jpeg\""
  },
  {
    "Name": "Mehmet ASLAN",
    "Birth Information": "KULP - 1979",
    "Organization": "PKK/KCK Terör Örgütü",
    "Photo URL": "\"/kurumlar/terorarananlar.pol.tr/Arsiv/472/FotoOrj.jpeg\""
  },
  {
    "Name": "SELMA SÜRER",
    "Birth Information": "CEYLANPINAR - 1973",
    "Organization": "PKK/KCK Terör Örgütü",
    "Photo URL": "\"/kurumlar/terorarananlar.pol.tr/33KOMISYON/SELMA-SURER.jpg\""
  },
  {
    "Name": "Zeliha TİTREK",
    "Birth Information": "KULU - 1971",
    "Organization": "PKK/KCK Terör Örgütü",
    "Photo URL": "\"/kurumlar/terorarananlar.pol.tr/36_KOMISYON/ZELIHA-TITREK.jpg\""
  },
  {
    "Name": "Murat DEMİR",
    "Birth Information": "AGRI - 1983",
    "Organization": "PKK/KCK Terör Örgütü",
    "Photo URL": "\"/kurumlar/terorarananlar.pol.tr/Arsiv/231/FotoOrj.jpeg\""
  },
  {
    "Name": "Ahmet KAHRAMAN",
    "Birth Information": "SİLOPİ - 1971",
    "Organization": "PKK/KCK Terör Örgütü",
    "Photo URL": "\"/kurumlar/terorarananlar.pol.tr/31KOMISYON/96_AHMET-KAHRAMAN.jpg\""
  },
  {
    "Name": "Bayram SAATÇİ",
    "Birth Information": "İSTANBUL - 1970",
    "Organization": "FETÖ/PDY Terör Örgütü",
    "Photo URL": "\"/kurumlar/terorarananlar.pol.tr/31KOMISYON/166_BAYRAM-SAATCI.jpg\""
  },
  {
    "Name": "Mehmet SİNCER",
    "Birth Information": "İVRİNDİ - 1978",
    "Organization": "FETÖ/PDY Terör Örgütü",
    "Photo URL": "\"/kurumlar/terorarananlar.pol.tr/31KOMISYON/161_MEHMET-SINCER-.jpg\""
  },
  {
    "Name": "Gökhan DEMİR",
    "Birth Information": "KELKİT - 1975",
    "Organization": "FETÖ/PDY Terör Örgütü",
    "Photo URL": "\"/kurumlar/terorarananlar.pol.tr/31KOMISYON/186_GOKHAN-DEMIR.jpg\""
  },
  {
    "Name": "Mehmet YILMAZ",
    "Birth Information": "SARAYÖNÜ - 1971",
    "Organization": "FETÖ/PDY Terör Örgütü",
    "Photo URL": "\"/kurumlar/terorarananlar.pol.tr/31KOMISYON/190_MEHMET-YILMAZ.jpg\""
  },
  {
    "Name": "Susan KIYGA",
    "Birth Information": "IĞDIR - 1991",
    "Organization": "PKK/KCK Terör Örgütü",
    "Photo URL": "\"/kurumlar/terorarananlar.pol.tr/SUSAN-KIYGA.jpg\""
  },
  {
    "Name": "Mehmet Emin  KUŞCU",
    "Birth Information": "KAYSERİ - 1982",
    "Organization": "FETÖ/PDY Terör Örgütü",
    "Photo URL": "\"/kurumlar/terorarananlar.pol.tr/31KOMISYON/203-MEHMET-EMIN-KUSCU_3.jpg\""
  },
  {
    "Name": "Çetin SABUNCİ",
    "Birth Information": "BORNOVA - 1976",
    "Organization": "FETÖ/PDY Terör Örgütü",
    "Photo URL": "\"/kurumlar/terorarananlar.pol.tr/31KOMISYON/199_CETIN-SABUNCU.jpg\""
  },
  {
    "Name": "Abdulkadir BAŞARAN",
    "Birth Information": "KULU - 1982",
    "Organization": "FETÖ/PDY Terör Örgütü",
    "Photo URL": "\"/kurumlar/terorarananlar.pol.tr/31KOMISYON/532_-ABDULKADIR-BASARAN-.jpg\""
  },
  {
    "Name": "Sancak DEMİRCİ",
    "Birth Information": "NARMAN - 1971",
    "Organization": "FETÖ/PDY Terör Örgütü",
    "Photo URL": "\"/kurumlar/terorarananlar.pol.tr/31KOMISYON/766_SANCAK-DEMIRCI.jpg\""
  },
  {
    "Name": "Ayhan TEKİNEŞ",
    "Birth Information": "KURUCA/ŞİLE - 1964",
    "Organization": "FETÖ/PDY Terör Örgütü",
    "Photo URL": "\"/kurumlar/terorarananlar.pol.tr/36_KOMISYON/ayhan-tekines.jpg\""
  },
  {
    "Name": "Mehmet ÇETİN",
    "Birth Information": "AKKISLA - 1997",
    "Organization": "DEAŞ Terör Örgütü",
    "Photo URL": "\"/kurumlar/terorarananlar.pol.tr/Arsiv/1772/FotoOrj.jpeg\""
  },
  {
    "Name": "Abdulhalim KARATAŞ",
    "Birth Information": "YILDIZELI - 1975",
    "Organization": "FETÖ/PDY Terör Örgütü",
    "Photo URL": "\"/kurumlar/terorarananlar.pol.tr/Arsiv/1328/FotoOrj.jpeg\""
  },
  {
    "Name": "Erkan BÜLBÜL",
    "Birth Information": "ÜSKÜDAR - 1976",
    "Organization": "DHKP/C Terör Örgütü",
    "Photo URL": "\"/kurumlar/terorarananlar.pol.tr/Arsiv/827/FotoOrj.jpeg\""
  },
  {
    "Name": "Ali KAHYA",
    "Birth Information": "BALA - 1979",
    "Organization": "FETÖ/PDY Terör Örgütü",
    "Photo URL": "\"/kurumlar/terorarananlar.pol.tr/Arsiv/1239/FotoOrj.jpeg\""
  },
  {
    "Name": "Faruk ARSLAN",
    "Birth Information": "ANKARA - 1969",
    "Organization": "FETÖ/PDY Terör Örgütü",
    "Photo URL": "\"/kurumlar/terorarananlar.pol.tr/31KOMISYON/498_-FARUK-ARSLAN.jpg\""
  },
  {
    "Name": "Salih TINMAZ",
    "Birth Information": "KIRKLARELİ - 1980",
    "Organization": "FETÖ/PDY Terör Örgütü",
    "Photo URL": "\"/kurumlar/terorarananlar.pol.tr/31KOMISYON/764_SALIH-TINMAZ.jpg\""
  },
  {
    "Name": "Betül AYDIN",
    "Birth Information": "GENÇ - 1997",
    "Organization": "PKK/KCK Terör Örgütü",
    "Photo URL": "\"/kurumlar/terorarananlar.pol.tr/31KOMISYON/433_-BETUL-AYDIN.jpg\""
  },
  {
    "Name": "İbrahim KOCABIYIK",
    "Birth Information": "SARIGÖL - 1951",
    "Organization": "FETÖ/PDY Terör Örgütü",
    "Photo URL": "\"/kurumlar/terorarananlar.pol.tr/Arsiv/186/FotoOrj.jpeg\""
  },
  {
    "Name": "Orhan ÜREK",
    "Birth Information": "ULUDERE - 1994",
    "Organization": "PKK/KCK Terör Örgütü",
    "Photo URL": "\"/kurumlar/terorarananlar.pol.tr/Arsiv/1804/FotoOrj.jpeg\""
  },
  {
    "Name": "Mehmet GÖK",
    "Birth Information": "ADANA - 1977",
    "Organization": "DEAŞ Terör Örgütü",
    "Photo URL": "\"/kurumlar/terorarananlar.pol.tr/Arsiv/1627/FotoOrj.jpeg\""
  },
  {
    "Name": "Erol GÜLTEKİN",
    "Birth Information": "İKİZDERE - 1959",
    "Organization": "TKP/ML Terör Örgütü",
    "Photo URL": "\"/kurumlar/terorarananlar.pol.tr/31KOMISYON/EROL-GULTEKIN.jpg\""
  },
  {
    "Name": "Cevdet TÜRKYOLU",
    "Birth Information": "ADAPAZARI - 1960",
    "Organization": "FETÖ/PDY Terör Örgütü",
    "Photo URL": "\"/kurumlar/terorarananlar.pol.tr/Arsiv/356/FotoOrj.jpeg\""
  },
  {
    "Name": "Mehmet Ali BÜYÜKÇELEBİ",
    "Birth Information": "TAVAS - 1950",
    "Organization": "FETÖ/PDY Terör Örgütü",
    "Photo URL": "\"/kurumlar/terorarananlar.pol.tr/Arsiv/787/FotoOrj.jpeg\""
  },
  {
    "Name": "Nurettin DEMİRTAS",
    "Birth Information": "PALU - 1972",
    "Organization": "PKK/KCK Terör Örgütü",
    "Photo URL": "\"/kurumlar/terorarananlar.pol.tr/Arsiv/70/FotoOrj_1.jpeg\""
  },
  {
    "Name": "VELİD HALİL",
    "Birth Information": "SURİYE - 1970",
    "Organization": "PKK/KCK Terör Örgütü",
    "Photo URL": "\"/kurumlar/terorarananlar.pol.tr/33KOMISYON/VELID-HALID.jpg\""
  },
  {
    "Name": "Müzgin ASLAN",
    "Birth Information": "ŞEMSİ - 1965",
    "Organization": "PKK/KCK Terör Örgütü",
    "Photo URL": "\"/kurumlar/terorarananlar.pol.tr/31KOMISYON/MUZGIN-ASLAN.jpg\""
  },
  {
    "Name": "Güleser TÖRÜN",
    "Birth Information": "KIGI - 1972",
    "Organization": "PKK/KCK Terör Örgütü",
    "Photo URL": "\"/kurumlar/terorarananlar.pol.tr/Arsiv/112/FotoOrj.jpeg\""
  },
  {
    "Name": "Oguzhan GÖZLEMECİOĞLU",
    "Birth Information": "ALTINDAG - 1980",
    "Organization": "DEAŞ Terör Örgütü",
    "Photo URL": "\"/kurumlar/terorarananlar.pol.tr/Arsiv/79/FotoOrj_1.jpeg\""
  },
  {
    "Name": "Yunus DEMİR",
    "Birth Information": "ŞEMDİNLİ - 1976",
    "Organization": "PKK/KCK Terör Örgütü",
    "Photo URL": "\"/kurumlar/terorarananlar.pol.tr/31KOMISYON/YUNUS-DEMIR.jpg\""
  },
  {
    "Name": "Ayşe TONĞUÇ",
    "Birth Information": "BAYKAN - 1971",
    "Organization": "PKK/KCK Terör Örgütü",
    "Photo URL": "\"/kurumlar/terorarananlar.pol.tr/Arsiv/1635/FotoOrj.jpeg\""
  },
  {
    "Name": "Besna KILIÇ",
    "Birth Information": "ERUH - 1983",
    "Organization": "PKK/KCK Terör Örgütü",
    "Photo URL": "\"/kurumlar/terorarananlar.pol.tr/30-KOMISYON/17_BESNA-KILIC.jpg\""
  },
  {
    "Name": "Remzi DEMİROĞLU",
    "Birth Information": "PAZARCIK - 1974",
    "Organization": "PKK/KCK Terör Örgütü",
    "Photo URL": "\"/kurumlar/terorarananlar.pol.tr/Arsiv/1081/FotoOrj.jpeg\""
  },
  {
    "Name": "Ramazan ABI",
    "Birth Information": "BEYTÜŞŞEBAP - 1976",
    "Organization": "PKK/KCK Terör Örgütü",
    "Photo URL": "\"/kurumlar/terorarananlar.pol.tr/30-KOMISYON/BOS.jpg\""
  },
  {
    "Name": "Hasan KANDEMİR",
    "Birth Information": "SURUÇ - 1981",
    "Organization": "PKK/KCK Terör Örgütü",
    "Photo URL": "\"/kurumlar/terorarananlar.pol.tr/28-KOMISYON/8_HASAN-KANDEMIR.jpg\""
  },
  {
    "Name": "Ronahi KARAHAN",
    "Birth Information": "DİYARBAKIR - 1994",
    "Organization": "PKK/KCK Terör Örgütü",
    "Photo URL": "\"/kurumlar/terorarananlar.pol.tr/28-KOMISYON/26_RONAHI-KARAHAN.jpg\""
  },
  {
    "Name": "Ekrem DUMANLI",
    "Birth Information": "YOZGAT - 1964",
    "Organization": "FETÖ/PDY Terör Örgütü",
    "Photo URL": "\"/kurumlar/terorarananlar.pol.tr/Arsiv/283/FotoOrj.jpeg\""
  },
  {
    "Name": "İbrahim Halil BAYLİ",
    "Birth Information": "BOZOVA - 1980",
    "Organization": "PKK/KCK Terör Örgütü",
    "Photo URL": "\"/kurumlar/terorarananlar.pol.tr/30-KOMISYON/2_IBRAHIM-BAYLI.jpg\""
  },
  {
    "Name": "Bilal KURUGÜL",
    "Birth Information": "IHSANIYE - 1976",
    "Organization": "FETÖ/PDY Terör Örgütü",
    "Photo URL": "\"/kurumlar/terorarananlar.pol.tr/Arsiv/1482/FotoOrj.jpeg\""
  },
  {
    "Name": "Emine TEMEL",
    "Birth Information": "SAVUR - 1986",
    "Organization": "PKK/KCK Terör Örgütü",
    "Photo URL": "\"/kurumlar/terorarananlar.pol.tr/Arsiv/1636/FotoOrj.jpeg\""
  },
  {
    "Name": "Sultan DAĞ",
    "Birth Information": "ÖMERLI - 1986",
    "Organization": "PKK/KCK Terör Örgütü",
    "Photo URL": "\"/kurumlar/terorarananlar.pol.tr/Arsiv/872/FotoOrj_1.jpeg\""
  },
  {
    "Name": "Ecevit PİROĞLU",
    "Birth Information": "HIRFANLI - 1974",
    "Organization": "DKP/BÖG Terör Örgütü",
    "Photo URL": "\"/kurumlar/terorarananlar.pol.tr/Arsiv/173/FotoOrj_1.jpeg\""
  },
  {
    "Name": "Süleyman ŞAHİN",
    "Birth Information": "TUNCELI - 1970",
    "Organization": "PKK/KCK Terör Örgütü",
    "Photo URL": "\"/kurumlar/terorarananlar.pol.tr/Arsiv/13/FotoOrj.jpeg\""
  },
  {
    "Name": "Mesut FIRAT",
    "Birth Information": "DEVELI - 1979",
    "Organization": "FETÖ/PDY Terör Örgütü",
    "Photo URL": "\"/kurumlar/terorarananlar.pol.tr/Arsiv/1481/FotoOrj.jpeg\""
  },
  {
    "Name": "Faysal ÇETİN",
    "Birth Information": "KOZLUK - 1983",
    "Organization": "PKK/KCK Terör Örgütü",
    "Photo URL": "\"/kurumlar/terorarananlar.pol.tr/31KOMISYON/FAYSAL-CETIN.jpg\""
  },
  {
    "Name": "Hatice AKTAŞ",
    "Birth Information": "BAKIRKÖY - 1971",
    "Organization": "PKK/KCK Terör Örgütü",
    "Photo URL": "\"/kurumlar/terorarananlar.pol.tr/Arsiv/122/FotoOrj.jpeg\""
  },
  {
    "Name": "Fatma ŞENPINAR",
    "Birth Information": "PAZARCIK - 1968",
    "Organization": "PKK/KCK Terör Örgütü",
    "Photo URL": "\"/kurumlar/terorarananlar.pol.tr/Arsiv/1589/FotoOrj.jpeg\""
  },
  {
    "Name": "Mihrac URAL",
    "Birth Information": "ANTAKYA - 1956",
    "Organization": "THKP/C Terör Örgütü",
    "Photo URL": "\"/kurumlar/terorarananlar.pol.tr/Arsiv/94/FotoOrj_1.jpeg\""
  },
  {
    "Name": "Müzeyyen GÜNEŞ",
    "Birth Information": "BULANIK - 1970",
    "Organization": "PKK/KCK Terör Örgütü",
    "Photo URL": "\"/kurumlar/terorarananlar.pol.tr/30-KOMISYON/29-MUZEYYEN-GUNES.jpg\""
  },
  {
    "Name": "Osman ŞİMŞEK",
    "Birth Information": "ALMUS - 1972",
    "Organization": "FETÖ/PDY Terör Örgütü",
    "Photo URL": "\"/kurumlar/terorarananlar.pol.tr/31KOMISYON/OSMAN-SIMSEK.jpg\""
  },
  {
    "Name": "Gülüzar TURAL",
    "Birth Information": "MALATYA - 1971",
    "Organization": "PKK/KCK Terör Örgütü",
    "Photo URL": "\"/kurumlar/terorarananlar.pol.tr/Arsiv/109/FotoOrj.jpeg\""
  },
  {
    "Name": "İsmet AKSOY",
    "Birth Information": "YENIKÖY - 1962",
    "Organization": "FETÖ/PDY Terör Örgütü",
    "Photo URL": "\"/kurumlar/terorarananlar.pol.tr/Arsiv/248/FotoOrj.jpeg\""
  },
  {
    "Name": "Hanife HÜSEYİN",
    "Birth Information": "null - null",
    "Organization": "PKK/KCK Terör Örgütü",
    "Photo URL": "\"/kurumlar/terorarananlar.pol.tr/36_KOMISYON/HANIFE-HUSEYIN.jpg\""
  },
  {
    "Name": "Abdullah AYMAZ",
    "Birth Information": "EMET - 1945",
    "Organization": "FETÖ/PDY Terör Örgütü",
    "Photo URL": "\"/kurumlar/terorarananlar.pol.tr/Arsiv/30/FotoOrj.jpeg\""
  },
  {
    "Name": "Abidin KARAKOÇ",
    "Birth Information": "DOGANSEHIR - 1967",
    "Organization": "PKK/KCK Terör Örgütü",
    "Photo URL": "\"/kurumlar/terorarananlar.pol.tr/Arsiv/124/FotoOrj.jpeg\""
  },
  {
    "Name": "Adem Serkan GÜNDOĞDU",
    "Birth Information": "ISTANBUL - 1977",
    "Organization": "MLKP Terör Örgütü",
    "Photo URL": "\"/kurumlar/terorarananlar.pol.tr/Arsiv/1674/FotoOrj.jpeg\""
  },
  {
    "Name": "Layika GÜLTEKİN",
    "Birth Information": "TUNCELI - 1974",
    "Organization": "PKK/KCK Terör Örgütü",
    "Photo URL": "\"/kurumlar/terorarananlar.pol.tr/Arsiv/17/FotoOrj.jpeg\""
  },
  {
    "Name": "Hatice AYDEMİR",
    "Birth Information": "ELBISTAN - 1970",
    "Organization": "MLKP Terör Örgütü",
    "Photo URL": "\"/kurumlar/terorarananlar.pol.tr/Arsiv/837/FotoOrj.jpeg\""
  },
  {
    "Name": "Gülten OĞUZ",
    "Birth Information": "YÜKSEKOVA - 1983",
    "Organization": "PKK/KCK Terör Örgütü",
    "Photo URL": "\"/kurumlar/terorarananlar.pol.tr/Arsiv/643/FotoOrj.jpeg\""
  },
  {
    "Name": "Arzu OK",
    "Birth Information": "ADIYAMAN - 1979",
    "Organization": "PKK/KCK Terör Örgütü",
    "Photo URL": "\"/kurumlar/terorarananlar.pol.tr/30-KOMISYON/16_ARZU-OK.jpg\""
  },
  {
    "Name": "Selman KUZU",
    "Birth Information": "ÇARSAMBA - 1965",
    "Organization": "FETÖ/PDY Terör Örgütü",
    "Photo URL": "\"/kurumlar/terorarananlar.pol.tr/Arsiv/188/FotoOrj.jpeg\""
  },
  {
    "Name": "Hüseyin Fevzi TEKİN",
    "Birth Information": "ISTANBUL - 1961",
    "Organization": "DHKP/C Terör Örgütü",
    "Photo URL": "\"/kurumlar/terorarananlar.pol.tr/Arsiv/82/FotoOrj.jpeg\""
  },
  {
    "Name": "Murat AŞIK",
    "Birth Information": "LANGENAU/ALMANYA - 1982",
    "Organization": "DHKP/C Terör Örgütü",
    "Photo URL": "\"/kurumlar/terorarananlar.pol.tr/Arsiv/1805/FotoOrj.jpeg\""
  },
  {
    "Name": "Mustafa ÇELİK",
    "Birth Information": "KARA - 1960",
    "Organization": "PKK/KCK Terör Örgütü",
    "Photo URL": "\"/kurumlar/terorarananlar.pol.tr/Arsiv/1651/FotoOrj.jpeg\""
  },
  {
    "Name": "Azad AKINCI",
    "Birth Information": "BATMAN - 1989",
    "Organization": "PKK/KCK Terör Örgütü",
    "Photo URL": "\"/kurumlar/terorarananlar.pol.tr/30-KOMISYON/44-AZAD-AKINCI.jpg\""
  },
  {
    "Name": "Yusuf KALKAN",
    "Birth Information": "ÇUKURCA - 1973",
    "Organization": "PKK/KCK Terör Örgütü",
    "Photo URL": "\"/kurumlar/terorarananlar.pol.tr/Arsiv/603/FotoOrj.jpeg\""
  },
  {
    "Name": "Şükriye DEMİR",
    "Birth Information": "MİDYAT - 1977",
    "Organization": "PKK/KCK Terör Örgütü",
    "Photo URL": "\"/kurumlar/terorarananlar.pol.tr/30-KOMISYON/10_SUKRIYE-DEMIR.jpg\""
  },
  {
    "Name": "Aysun ÇAMDALI",
    "Birth Information": "GAZIANTEP - 1976",
    "Organization": "PKK/KCK Terör Örgütü",
    "Photo URL": "\"/kurumlar/terorarananlar.pol.tr/Arsiv/1610/FotoOrj_1.jpeg\""
  },
  {
    "Name": "Arap GÜLENÇ",
    "Birth Information": "ŞIRNAK - 1973",
    "Organization": "PKK/KCK Terör Örgütü",
    "Photo URL": "\"/kurumlar/terorarananlar.pol.tr/31KOMISYON/ARAP-GULENC.jpg\""
  },
  {
    "Name": "Deniz BÜYÜKÇELEBİ",
    "Birth Information": "NIZIP - 1978",
    "Organization": "DEAŞ Terör Örgütü",
    "Photo URL": "\"/kurumlar/terorarananlar.pol.tr/Arsiv/129/FotoOrj_1.jpeg\""
  },
  {
    "Name": "Yılmaz ÖNER",
    "Birth Information": "MALAZGIRT - 1975",
    "Organization": "PKK/KCK Terör Örgütü",
    "Photo URL": "\"/kurumlar/terorarananlar.pol.tr/Ilgi-Yazi-ve-Ekleri.PNG\""
  },
  {
    "Name": "Zerrin SARI",
    "Birth Information": "OSMANIYE - 1963",
    "Organization": "DHKP/C Terör Örgütü",
    "Photo URL": "\"/kurumlar/terorarananlar.pol.tr/Arsiv/24/FotoOrj.jpeg\""
  },
  {
    "Name": "İmam CANDAN",
    "Birth Information": "OVACIK - 1962",
    "Organization": "MKP Terör Örgütü",
    "Photo URL": "\"/kurumlar/terorarananlar.pol.tr/Arsiv/87/FotoOrj_1.jpeg\""
  },
  {
    "Name": "Hacire ATEŞ",
    "Birth Information": "DIYARBAKIR - 1977",
    "Organization": "PKK/KCK Terör Örgütü",
    "Photo URL": "\"/kurumlar/terorarananlar.pol.tr/Arsiv/56/FotoOrj.jpeg\""
  },
  {
    "Name": "Lokman TOPRAK",
    "Birth Information": "ERKENT - 1977",
    "Organization": "PKK/KCK Terör Örgütü",
    "Photo URL": "\"/kurumlar/terorarananlar.pol.tr/Arsiv/75/FotoOrj.jpeg\""
  },
  {
    "Name": "Güzel İMECİK",
    "Birth Information": "IDIL - 1978",
    "Organization": "PKK/KCK Terör Örgütü",
    "Photo URL": "\"/kurumlar/terorarananlar.pol.tr/Arsiv/1544/FotoOrj.jpeg\""
  },
  {
    "Name": "Melihet KALKAN",
    "Birth Information": "YEŞİLALAN - 1979",
    "Organization": "PKK/KCK Terör Örgütü",
    "Photo URL": "\"/kurumlar/terorarananlar.pol.tr/36_KOMISYON/MELIHET-KALKAN.jpg\""
  },
  {
    "Name": "Sadettin DEDE",
    "Birth Information": "YÜKSEKOVA - 1973",
    "Organization": "PKK/KCK Terör Örgütü",
    "Photo URL": "\"/kurumlar/terorarananlar.pol.tr/Arsiv/119/FotoOrj.jpeg\""
  },
  {
    "Name": "Faruk EREREN",
    "Birth Information": "ÜNYE - 1955",
    "Organization": "DHKP/C Terör Örgütü",
    "Photo URL": "\"/kurumlar/terorarananlar.pol.tr/Arsiv/29/FotoOrj.jpeg\""
  },
  {
    "Name": "Gazi BAHADIR",
    "Birth Information": "BEYTÜSSEBAP - 1983",
    "Organization": "PKK/KCK Terör Örgütü",
    "Photo URL": "\"/kurumlar/terorarananlar.pol.tr/Arsiv/389/FotoOrj.jpeg\""
  },
  {
    "Name": "Şenay ORUÇ",
    "Birth Information": "AHLAT - 1975",
    "Organization": "PKK/KCK Terör Örgütü",
    "Photo URL": "\"/kurumlar/terorarananlar.pol.tr/Arsiv/59/FotoOrj.jpeg\""
  },
  {
    "Name": "Mehmet Vehbi YAVUZLAR",
    "Birth Information": "ATABEY - 1957",
    "Organization": "FETÖ/PDY Terör Örgütü",
    "Photo URL": "\"/kurumlar/terorarananlar.pol.tr/31KOMISYON/359_MEHMET-VEHBI-YAVUZLAR.jpg\""
  },
  {
    "Name": "Ali BAYRAM",
    "Birth Information": "HASANKALE - 1953",
    "Organization": "FETÖ/PDY Terör Örgütü",
    "Photo URL": "\"/kurumlar/terorarananlar.pol.tr/Arsiv/189/FotoOrj.jpeg\""
  },
  {
    "Name": "Gurbet KARA",
    "Birth Information": "ULUDERE - 1982",
    "Organization": "PKK/KCK Terör Örgütü",
    "Photo URL": "\"/kurumlar/terorarananlar.pol.tr/30-KOMISYON/7_GURBET-KARA.jpg\""
  },
  {
    "Name": "Mehmet ŞAKAR",
    "Birth Information": "İDİL - 1978",
    "Organization": "PKK/KCK Terör Örgütü",
    "Photo URL": "\"/kurumlar/terorarananlar.pol.tr/31KOMISYON/33MEHMET-SAKAR.jpg\""
  },
  {
    "Name": "Lokman BULUT",
    "Birth Information": "NUSAYBİN - 1977",
    "Organization": "PKK/KCK Terör Örgütü",
    "Photo URL": "\"/kurumlar/terorarananlar.pol.tr/36_KOMISYON/LOKMAN-BULUT.jpg\""
  },
  {
    "Name": "Necibe ÖMER",
    "Birth Information": "Bagdat - 1971",
    "Organization": "PKK/KCK Terör Örgütü",
    "Photo URL": "\"/kurumlar/terorarananlar.pol.tr/Arsiv/1798/FotoOrj.jpeg\""
  },
  {
    "Name": "Süleyman SARGIN",
    "Birth Information": "KEMALPAŞA - 1974",
    "Organization": "FETÖ/PDY Terör Örgütü",
    "Photo URL": "\"/kurumlar/terorarananlar.pol.tr/31KOMISYON/524_-SULEYMAN-SARGIN.jpg\""
  },
  {
    "Name": "Nuri ERYÜKSEL",
    "Birth Information": "GÜMÜSHACIKÖY - 1958",
    "Organization": "DHKP/C Terör Örgütü",
    "Photo URL": "\"/kurumlar/terorarananlar.pol.tr/Arsiv/38/FotoOrj.jpeg\""
  },
  {
    "Name": "Habib AKDAŞ",
    "Birth Information": "SAVUR - 1973",
    "Organization": "EL KAİDE Terör Örgütü",
    "Photo URL": "\"/kurumlar/terorarananlar.pol.tr/Arsiv/130/FotoOrj_1.jpeg\""
  },
  {
    "Name": "Ali TOPRAK",
    "Birth Information": "ERKENT - 1981",
    "Organization": "PKK/KCK Terör Örgütü",
    "Photo URL": "\"/kurumlar/terorarananlar.pol.tr/36_KOMISYON/ALI-TOPRAK.jpg\""
  },
  {
    "Name": "Leyla AHMED",
    "Birth Information": "null - null",
    "Organization": "PKK/KCK Terör Örgütü",
    "Photo URL": "\"/kurumlar/terorarananlar.pol.tr/36_KOMISYON/LEYLA-AHMED.jpg\""
  },
  {
    "Name": "Remziye COLAK",
    "Birth Information": "Zivikan - 1980",
    "Organization": "PKK/KCK Terör Örgütü",
    "Photo URL": "\"/kurumlar/terorarananlar.pol.tr/Arsiv/1802/FotoOrj.jpeg\""
  },
  {
    "Name": "Nesrin DENİZ",
    "Birth Information": "HİLVAN - 1979",
    "Organization": "PKK/KCK Terör Örgütü",
    "Photo URL": "\"/kurumlar/terorarananlar.pol.tr/NESRIN-DENIZ.jpg\""
  },
  {
    "Name": "Gazal KAYMAZ",
    "Birth Information": "BATMAN - 1997",
    "Organization": "PKK/KCK Terör Örgütü",
    "Photo URL": "\"/kurumlar/terorarananlar.pol.tr/28-KOMISYON/28_GAZAL-KAYMAZ.jpg\""
  },
  {
    "Name": "Ziya ULUSOY",
    "Birth Information": "OVACIK - 1953",
    "Organization": "MLKP Terör Örgütü",
    "Photo URL": "\"/kurumlar/terorarananlar.pol.tr/Arsiv/89/FotoOrj.jpeg\""
  },
  {
    "Name": "İlyas AYDIN",
    "Birth Information": "FATIH - 1989",
    "Organization": "DEAŞ Terör Örgütü",
    "Photo URL": "\"/kurumlar/terorarananlar.pol.tr/Arsiv/274/FotoOrj_1.jpeg\""
  },
  {
    "Name": "Haşim ALABALIK",
    "Birth Information": "DIYARBAKIR - 1976",
    "Organization": "HİZBULLAH Terör Örgütü",
    "Photo URL": "\"/kurumlar/terorarananlar.pol.tr/Arsiv/1629/FotoOrj.jpeg\""
  },
  {
    "Name": "İsmail BÜYÜKÇELEBİ",
    "Birth Information": "TAVAS - 1951",
    "Organization": "FETÖ/PDY Terör Örgütü",
    "Photo URL": "\"/kurumlar/terorarananlar.pol.tr/Arsiv/32/FotoOrj.jpeg\""
  },
  {
    "Name": "Emine SERİNYEL",
    "Birth Information": "KIGI - 1979",
    "Organization": "PKK/KCK Terör Örgütü",
    "Photo URL": "\"/kurumlar/terorarananlar.pol.tr/Arsiv/114/FotoOrj.jpeg\""
  },
  {
    "Name": "Bedirhan ABO",
    "Birth Information": "BEYTÜSSEBAP - 1979",
    "Organization": "PKK/KCK Terör Örgütü",
    "Photo URL": "\"/kurumlar/terorarananlar.pol.tr/Arsiv/106/FotoOrj.jpeg\""
  },
  {
    "Name": "Süleyman ÖZKAYNAKCI",
    "Birth Information": "SIVAS - 1982",
    "Organization": "FETÖ/PDY Terör Örgütü",
    "Photo URL": "\"/kurumlar/terorarananlar.pol.tr/Arsiv/1486/FotoOrj.jpeg\""
  },
  {
    "Name": "Onur DÜNDAR",
    "Birth Information": "ZARA - 1986",
    "Organization": "MKP Terör Örgütü",
    "Photo URL": "\"/kurumlar/terorarananlar.pol.tr/Arsiv/1681/FotoOrj.jpeg\""
  },
  {
    "Name": "Necdet BAŞARAN",
    "Birth Information": "ALACA - 1945",
    "Organization": "FETÖ/PDY Terör Örgütü",
    "Photo URL": "\"/kurumlar/terorarananlar.pol.tr/Arsiv/164/FotoOrj.jpeg\""
  },
  {
    "Name": "Müslüm BAYAT",
    "Birth Information": "PALU - 1978",
    "Organization": "PKK/KCK Terör Örgütü",
    "Photo URL": "\"/kurumlar/terorarananlar.pol.tr/Arsiv/1049/FotoOrj.jpeg\""
  },
  {
    "Name": "Eren TEMEL",
    "Birth Information": "VARTO/SEKİ - 1976",
    "Organization": "PKK/KCK Terör Örgütü",
    "Photo URL": "\"/kurumlar/terorarananlar.pol.tr/31KOMISYON/EREN-TEMEL.jpg\""
  },
  {
    "Name": "Bilen ENCU",
    "Birth Information": "ULUDERE - 1992",
    "Organization": "PKK/KCK Terör Örgütü",
    "Photo URL": "\"/kurumlar/terorarananlar.pol.tr/30-KOMISYON/80-BILEN-ENCU.jpg\""
  },
  {
    "Name": "Cemile ÇELİK",
    "Birth Information": "MİDYAT - 1982",
    "Organization": "PKK/KCK Terör Örgütü",
    "Photo URL": "\"/kurumlar/terorarananlar.pol.tr/31KOMISYON/CEMILE-CICEK.jpg\""
  },
  {
    "Name": "Gülnaz ERGÖNÜL",
    "Birth Information": "OSMANIYE - 1973",
    "Organization": "PKK/KCK Terör Örgütü",
    "Photo URL": "\"/kurumlar/terorarananlar.pol.tr/Arsiv/1633/FotoOrj.jpeg\""
  },
  {
    "Name": "İbrahim KEPEZ",
    "Birth Information": "ELBISTAN - 1961",
    "Organization": "MLKP Terör Örgütü",
    "Photo URL": "\"/kurumlar/terorarananlar.pol.tr/Arsiv/43/FotoOrj.jpeg\""
  },
  {
    "Name": "CENGİZ KIZILTAŞ",
    "Birth Information": "TUZLUCA - 1972",
    "Organization": "PKK/KCK Terör Örgütü",
    "Photo URL": "\"/kurumlar/terorarananlar.pol.tr/33KOMISYON/CENGIZ-KIZILTAS.jpg\""
  },
  {
    "Name": "Esmer AYAZ",
    "Birth Information": "ORTACA - 1973",
    "Organization": "PKK/KCK Terör Örgütü",
    "Photo URL": "\"/kurumlar/terorarananlar.pol.tr/Arsiv/1595/FotoOrj.jpeg\""
  },
  {
    "Name": "KATİBE DUMAN",
    "Birth Information": "MİDYAT - 1976",
    "Organization": "PKK/KCK Terör Örgütü",
    "Photo URL": "\"/kurumlar/terorarananlar.pol.tr/30-KOMISYON/25-KATIBE-DUMAN.jpg\""
  },
  {
    "Name": "Raif ÇİFTÇİ",
    "Birth Information": "HAKKARİ - 1975",
    "Organization": "PKK/KCK Terör Örgütü",
    "Photo URL": "\"/kurumlar/terorarananlar.pol.tr/30-KOMISYON/4_RAIF-CIFTCI.jpg\""
  },
  {
    "Name": "Leyla ARSLAN",
    "Birth Information": "DİYARBAKIR - 1989",
    "Organization": "PKK/KCK Terör Örgütü",
    "Photo URL": "\"/kurumlar/terorarananlar.pol.tr/30-KOMISYON/48-LEYLA-ARSLAN.jpg\""
  },
  {
    "Name": "MUHAMMED ÇETİN",
    "Birth Information": "ESKİŞEHİR - 1963",
    "Organization": "FETÖ/PDY Terör Örgütü",
    "Photo URL": "\"/kurumlar/terorarananlar.pol.tr/33KOMISYON/MUHAMMED-CETIN.jpg\""
  },
  {
    "Name": "Yasemin BECEREKLİ",
    "Birth Information": "SILVAN - 1974",
    "Organization": "PKK/KCK Terör Örgütü",
    "Photo URL": "\"/kurumlar/terorarananlar.pol.tr/Arsiv/1594/FotoOrj.jpeg\""
  },
  {
    "Name": "Şadi Naci ÖZPOLAT",
    "Birth Information": "KAHRAMANMARAS - 1969",
    "Organization": "DHKP/C Terör Örgütü",
    "Photo URL": "\"/kurumlar/terorarananlar.pol.tr/Arsiv/39/FotoOrj.jpeg\""
  },
  {
    "Name": "Elif YILDIRIM",
    "Birth Information": "PAZARCIK - 1964",
    "Organization": "PKK/KCK Terör Örgütü",
    "Photo URL": "\"/kurumlar/terorarananlar.pol.tr/Arsiv/10/FotoOrj.jpeg\""
  },
  {
    "Name": "Garabit DEMİRCİ",
    "Birth Information": "SARNIS - 1958",
    "Organization": "TKP-ML Konferans Terör Örgütü",
    "Photo URL": "\"/kurumlar/terorarananlar.pol.tr/Arsiv/1680/FotoOrj.jpeg\""
  },
  {
    "Name": "İhsan YİĞİT",
    "Birth Information": "İDİL - 1980",
    "Organization": "PKK/KCK Terör Örgütü",
    "Photo URL": "\"/kurumlar/terorarananlar.pol.tr/31KOMISYON/252-IHSAN-YIGIT.jpg\""
  },
  {
    "Name": "Filiz SADIKOĞLU",
    "Birth Information": "MAZIDAGI - 1976",
    "Organization": "PKK/KCK Terör Örgütü",
    "Photo URL": "\"/kurumlar/terorarananlar.pol.tr/Arsiv/1637/FotoOrj.jpeg\""
  },
  {
    "Name": "Kenan AYDIN",
    "Birth Information": "ARPAÇAY - 1966",
    "Organization": "PKK/KCK Terör Örgütü",
    "Photo URL": "\"/kurumlar/terorarananlar.pol.tr/KENAN-AYDIN.jpg\""
  },
  {
    "Name": "Hediye ALTUN",
    "Birth Information": "SAVUR - 1977",
    "Organization": "PKK/KCK Terör Örgütü",
    "Photo URL": "\"/kurumlar/terorarananlar.pol.tr/31KOMISYON/95_HEDIYE-ALTUN.jpg\""
  },
  {
    "Name": "Ali BOR",
    "Birth Information": "YÜKSEKOVA - 1980",
    "Organization": "PKK/KCK Terör Örgütü",
    "Photo URL": "\"/kurumlar/terorarananlar.pol.tr/Arsiv/1619/FotoOrj.jpeg\""
  },
  {
    "Name": "Yusuf ŞEK",
    "Birth Information": "ARALIK - 1974",
    "Organization": "PKK/KCK Terör Örgütü",
    "Photo URL": "\"/kurumlar/terorarananlar.pol.tr/Arsiv/100/FotoOrj.jpeg\""
  },
  {
    "Name": "Halit ESENDİR",
    "Birth Information": "KOCAHIDIR - 1955",
    "Organization": "FETÖ/PDY Terör Örgütü",
    "Photo URL": "\"/kurumlar/terorarananlar.pol.tr/Arsiv/783/FotoOrj.jpeg\""
  },
  {
    "Name": "Naci GÜNER",
    "Birth Information": "ERZINCAN - 1952",
    "Organization": "MLKP Terör Örgütü",
    "Photo URL": "\"/kurumlar/terorarananlar.pol.tr/Arsiv/90/FotoOrj.jpeg\""
  },
  {
    "Name": "Sultan ULUSOY",
    "Birth Information": "SARIZ - 1969",
    "Organization": "MLKP Terör Örgütü",
    "Photo URL": "\"/kurumlar/terorarananlar.pol.tr/Arsiv/1675/FotoOrj.jpeg\""
  },
  {
    "Name": "Gülten ALATAŞ",
    "Birth Information": "MALATYA - 1965",
    "Organization": "PKK/KCK Terör Örgütü",
    "Photo URL": "\"/kurumlar/terorarananlar.pol.tr/Arsiv/57/FotoOrj_1.jpeg\""
  },
  {
    "Name": "Azime YILMAZ",
    "Birth Information": "HOZAT - 1966",
    "Organization": "PKK/KCK Terör Örgütü",
    "Photo URL": "\"/kurumlar/terorarananlar.pol.tr/Arsiv/1603/FotoOrj.jpeg\""
  },
  {
    "Name": "Adil ÖKSÜZ",
    "Birth Information": "ANDIRIN - 1967",
    "Organization": "FETÖ/PDY Terör Örgütü",
    "Photo URL": "\"/kurumlar/terorarananlar.pol.tr/Arsiv/37/FotoOrj.jpeg\""
  },
  {
    "Name": "Nihat DURMUŞ",
    "Birth Information": "SURUÇ - 1971",
    "Organization": "PKK/KCK Terör Örgütü",
    "Photo URL": "\"/kurumlar/terorarananlar.pol.tr/31KOMISYON/NIHAT-DURMUS.jpg\""
  },
  {
    "Name": "Hamdullah Bayram ÖZTÜRK",
    "Birth Information": "SORGUN - 1967",
    "Organization": "FETÖ/PDY Terör Örgütü",
    "Photo URL": "\"/kurumlar/terorarananlar.pol.tr/Arsiv/785/FotoOrj.jpeg\""
  },
  {
    "Name": "Nilüfer ÇOBAN",
    "Birth Information": "BAKIRKÖY - 1978",
    "Organization": "PKK/KCK Terör Örgütü",
    "Photo URL": "\"/kurumlar/terorarananlar.pol.tr/Arsiv/71/FotoOrj_1.jpeg\""
  },
  {
    "Name": "Hasan AYDIN",
    "Birth Information": "YÜREGIR - 1988",
    "Organization": "DEAŞ Terör Örgütü",
    "Photo URL": "\"/kurumlar/terorarananlar.pol.tr/Arsiv/128/FotoOrj_1.jpeg\""
  },
  {
    "Name": "Ramazan AYGÜN",
    "Birth Information": "PÜTÜRGE - 1980",
    "Organization": "FETÖ/PDY Terör Örgütü",
    "Photo URL": "\"/kurumlar/terorarananlar.pol.tr/31KOMISYON/74RAMAZAN-AYGUN.jpg\""
  },
  {
    "Name": "İjlal ATAK",
    "Birth Information": "YÜKSEKOVA - 1991",
    "Organization": "PKK/KCK Terör Örgütü",
    "Photo URL": "\"/kurumlar/terorarananlar.pol.tr/33KOMISYON/IJLAL-ATAK.jpg\""
  },
  {
    "Name": "Oğuz DEMİR",
    "Birth Information": "ANKARA - 1971",
    "Organization": "TEVHİD-SELAM KUDÜS ORDUSU Terör Örgütü",
    "Photo URL": "\"/kurumlar/terorarananlar.pol.tr/Arsiv/205/FotoOrj.jpeg\""
  },
  {
    "Name": "Ahmet KURUCAN",
    "Birth Information": "TAVSANLI - 1961",
    "Organization": "FETÖ/PDY Terör Örgütü",
    "Photo URL": "\"/kurumlar/terorarananlar.pol.tr/Arsiv/184/FotoOrj_1.jpeg\""
  },
  {
    "Name": "İskan AKYÜZ",
    "Birth Information": "MIDYAT - 1973",
    "Organization": "PKK/KCK Terör Örgütü",
    "Photo URL": "\"/kurumlar/terorarananlar.pol.tr/Arsiv/126/FotoOrj.jpeg\""
  },
  {
    "Name": "Suat YILDIRIM",
    "Birth Information": "ERGANI - 1941",
    "Organization": "FETÖ/PDY Terör Örgütü",
    "Photo URL": "\"/kurumlar/terorarananlar.pol.tr/Arsiv/192/FotoOrj.jpeg\""
  },
  {
    "Name": "Necmettin SANLİ",
    "Birth Information": "ERGANI - 1969",
    "Organization": "HİZBULLAH Terör Örgütü",
    "Photo URL": "\"/kurumlar/terorarananlar.pol.tr/Arsiv/1624/FotoOrj.jpeg\""
  },
  {
    "Name": "Cengiz TÜCCAR",
    "Birth Information": "ARTOVA - 1966",
    "Organization": "FETÖ/PDY Terör Örgütü",
    "Photo URL": "\"/kurumlar/terorarananlar.pol.tr/31KOMISYON/CENGIZ-TUCCER.jpg\""
  },
  {
    "Name": "Ali Ekber DOĞAN",
    "Birth Information": "MADEN - 1973",
    "Organization": "MKP Terör Örgütü",
    "Photo URL": "\"/kurumlar/terorarananlar.pol.tr/Arsiv/84/FotoOrj.jpeg\""
  },
  {
    "Name": "Fawza El YUSUF",
    "Birth Information": "null - null",
    "Organization": "PKK/KCK Terör Örgütü",
    "Photo URL": "\"/kurumlar/terorarananlar.pol.tr/36_KOMISYON/FAWZA-EL-YUSUF.jpg\""
  },
  {
    "Name": "Bulut KİŞİN",
    "Birth Information": "BINGÖL - 1985",
    "Organization": "PKK/KCK Terör Örgütü",
    "Photo URL": "\"/kurumlar/terorarananlar.pol.tr/Arsiv/1153/FotoOrj.jpeg\""
  },
  {
    "Name": "Süleyman GÜLER",
    "Birth Information": "MİDYAT - 1989",
    "Organization": "PKK/KCK Terör Örgütü",
    "Photo URL": "\"/kurumlar/terorarananlar.pol.tr/28-KOMISYON/7_SULEYMAN-GULER.jpg\""
  },
  {
    "Name": "Cantürk BARAN",
    "Birth Information": "YÜKSEKOVA - 1988",
    "Organization": "PKK/KCK Terör Örgütü",
    "Photo URL": "\"/kurumlar/terorarananlar.pol.tr/28-KOMISYON/9_CANTURK-BARAN.jpg\""
  },
  {
    "Name": "Recep UZUNALLI",
    "Birth Information": "MENEMEN - 1954",
    "Organization": "FETÖ/PDY Terör Örgütü",
    "Photo URL": "\"/kurumlar/terorarananlar.pol.tr/Arsiv/358/FotoOrj.jpeg\""
  },
  {
    "Name": "Mehmet Can TEMEL",
    "Birth Information": "MAZIDAĞI - 1984",
    "Organization": "PKK/KCK Terör Örgütü",
    "Photo URL": "\"/kurumlar/terorarananlar.pol.tr/30-KOMISYON/13_MEHMET-CAN-TEMEL.jpg\""
  },
  {
    "Name": "Muhammed İBRAHİM",
    "Birth Information": "KOBANİ - 1990",
    "Organization": "PKK/KCK Terör Örgütü",
    "Photo URL": "\"/kurumlar/terorarananlar.pol.tr/31KOMISYON/MUHAMMED-IBRAHIM.jpg\""
  },
  {
    "Name": "Murat KARAYILAN",
    "Birth Information": "KONAK - 1954",
    "Organization": "PKK/KCK Terör Örgütü",
    "Photo URL": "\"/kurumlar/terorarananlar.pol.tr/Arsiv/2/FotoOrj.jpeg\""
  },
  {
    "Name": "Mehmet Akif UÇAR",
    "Birth Information": "ISLAHIYE - 1972",
    "Organization": "PKK/KCK Terör Örgütü",
    "Photo URL": "\"/kurumlar/terorarananlar.pol.tr/Arsiv/1601/FotoOrj.jpeg\""
  },
  {
    "Name": "Seher DEMİR",
    "Birth Information": "KOZLU - 1959",
    "Organization": "DHKP/C Terör Örgütü",
    "Photo URL": "\"/kurumlar/terorarananlar.pol.tr/Arsiv/83/FotoOrj.jpeg\""
  },
  {
    "Name": "Müslüm ELMA",
    "Birth Information": "PERTEK - 1960",
    "Organization": "TKP/ML Terör Örgütü",
    "Photo URL": "\"/kurumlar/terorarananlar.pol.tr/31KOMISYON/233-MUSLUM-ELMA.jpg\""
  },
  {
    "Name": "Enver BAYRAM",
    "Birth Information": "BAŞKALE - 1975",
    "Organization": "PKK/KCK Terör Örgütü",
    "Photo URL": "\"/kurumlar/terorarananlar.pol.tr/28-KOMISYON/30_ENVER-BAYRAM.jpg\""
  },
  {
    "Name": "Mustafa DOKUMACI",
    "Birth Information": "ADANA - 1985",
    "Organization": "DEAŞ Terör Örgütü",
    "Photo URL": "\"/kurumlar/terorarananlar.pol.tr/Arsiv/28/FotoOrj_1.jpeg\""
  },
  {
    "Name": "Muhittin BÜYÜKYANGÖZ",
    "Birth Information": "KARATAY - 1989",
    "Organization": "DEAŞ Terör Örgütü",
    "Photo URL": "\"/kurumlar/terorarananlar.pol.tr/Arsiv/180/FotoOrj_1.jpeg\""
  },
  {
    "Name": "Müzeyyen AYDINLI",
    "Birth Information": "KURTALAN - 1976",
    "Organization": "PKK/KCK Terör Örgütü",
    "Photo URL": "\"/kurumlar/terorarananlar.pol.tr/Arsiv/77/FotoOrj.jpeg\""
  },
  {
    "Name": "Aynur HÜLAKÜ",
    "Birth Information": "SILVAN - 1971",
    "Organization": "PKK/KCK Terör Örgütü",
    "Photo URL": "\"/kurumlar/terorarananlar.pol.tr/Arsiv/1599/FotoOrj.jpeg\""
  },
  {
    "Name": "Ramazan ÖKTÜLMÜŞ",
    "Birth Information": "GERGER - 1958",
    "Organization": "MKP Terör Örgütü",
    "Photo URL": "\"/kurumlar/terorarananlar.pol.tr/Arsiv/42/FotoOrj.jpeg\""
  },
  {
    "Name": "Talip AKKURT",
    "Birth Information": "GAZIANTEP - 1981",
    "Organization": "DEAŞ Terör Örgütü",
    "Photo URL": "\"/kurumlar/terorarananlar.pol.tr/Arsiv/181/FotoOrj_1.jpeg\""
  },
  {
    "Name": "Mehmet Sadık KAYA",
    "Birth Information": "NUSAYBİN - 1989",
    "Organization": "PKK/KCK Terör Örgütü",
    "Photo URL": "\"/kurumlar/terorarananlar.pol.tr/30-KOMISYON/BOS.jpg\""
  },
  {
    "Name": "Fatma DEMİR",
    "Birth Information": "null - null",
    "Organization": "PKK/KCK Terör Örgütü",
    "Photo URL": "\"/kurumlar/terorarananlar.pol.tr/36_KOMISYON/FATMA-DEMIR.jpg\""
  },
  {
    "Name": "Gençay BÖYÜK",
    "Birth Information": "SENKAYA - 1977",
    "Organization": "FETÖ/PDY Terör Örgütü",
    "Photo URL": "\"/kurumlar/terorarananlar.pol.tr/Arsiv/1488/FotoOrj.jpeg\""
  },
  {
    "Name": "Nazan ATAŞ",
    "Birth Information": "BENLIKAYA - 1978",
    "Organization": "PKK/KCK Terör Örgütü",
    "Photo URL": "\"/kurumlar/terorarananlar.pol.tr/Arsiv/273/FotoOrj.jpeg\""
  },
  {
    "Name": "Arzu KAHRIMAN",
    "Birth Information": "INEGÖL - 1975",
    "Organization": "PKK/KCK Terör Örgütü",
    "Photo URL": "\"/kurumlar/terorarananlar.pol.tr/Arsiv/328/FotoOrj.jpeg\""
  },
  {
    "Name": "Hüseyin YAĞMUR",
    "Birth Information": "KAHRAMANMARAŞ - 1965",
    "Organization": "FETÖ/PDY Terör Örgütü",
    "Photo URL": "\"/kurumlar/terorarananlar.pol.tr/31KOMISYON/639_HUSEYIN-YAGMUR.jpg\""
  },
  {
    "Name": "Celalettin GÜN",
    "Birth Information": "MİDYAT - 1976",
    "Organization": "PKK/KCK Terör Örgütü",
    "Photo URL": "\"/kurumlar/terorarananlar.pol.tr/30-KOMISYON/14_CELALETTIN-GUN.jpg\""
  },
  {
    "Name": "Halim ÖZKAN",
    "Birth Information": "ERUH - 1978",
    "Organization": "PKK/KCK Terör Örgütü",
    "Photo URL": "\"/kurumlar/terorarananlar.pol.tr/HALIM-OZKAN.jpg\""
  },
  {
    "Name": "Haydar KUTAN",
    "Birth Information": "TUNCELİ - 1954",
    "Organization": "MKP Terör Örgütü",
    "Photo URL": "\"/kurumlar/terorarananlar.pol.tr/31KOMISYON/Adsiz.jpg\""
  },
  {
    "Name": "Serkan NAZLİER",
    "Birth Information": "DIYARBAKIR - 1986",
    "Organization": "PKK/KCK Terör Örgütü",
    "Photo URL": "\"/kurumlar/terorarananlar.pol.tr/Arsiv/1691/FotoOrj.jpeg\""
  },
  {
    "Name": "Edip GÜMÜŞ",
    "Birth Information": "AKSU - 1958",
    "Organization": "HİZBULLAH Terör Örgütü",
    "Photo URL": "\"/kurumlar/terorarananlar.pol.tr/Arsiv/131/FotoOrj_1.jpeg\""
  },
  {
    "Name": "Semir ASU",
    "Birth Information": "null - null",
    "Organization": "PKK/KCK Terör Örgütü",
    "Photo URL": "\"/kurumlar/terorarananlar.pol.tr/36_KOMISYON/SEMIR-ASU.jpg\""
  },
  {
    "Name": "Seyran ÇOMAK",
    "Birth Information": "BASKALE - 1984",
    "Organization": "PKK/KCK Terör Örgütü",
    "Photo URL": "\"/kurumlar/terorarananlar.pol.tr/Arsiv/175/FotoOrj_1.jpeg\""
  },
  {
    "Name": "Necdet İÇEL",
    "Birth Information": "KORUCUK - 1955",
    "Organization": "FETÖ/PDY Terör Örgütü",
    "Photo URL": "\"/kurumlar/terorarananlar.pol.tr/Arsiv/165/FotoOrj.jpeg\""
  },
  {
    "Name": "Azime ARSUN",
    "Birth Information": "SİLOPİ - 1976",
    "Organization": "PKK/KCK Terör Örgütü",
    "Photo URL": "\"/kurumlar/terorarananlar.pol.tr/AZIME-ARSUN.jpg\""
  },
  {
    "Name": "Feruh YILDIRIM",
    "Birth Information": "SOLHAN - 1971",
    "Organization": "PKK/KCK Terör Örgütü",
    "Photo URL": "\"/kurumlar/terorarananlar.pol.tr/Arsiv/67/FotoOrj.jpeg\""
  },
  {
    "Name": "İsmet ALTIN",
    "Birth Information": "MANAVGAT - 1968",
    "Organization": "DEAŞ Terör Örgütü",
    "Photo URL": "\"/kurumlar/terorarananlar.pol.tr/Arsiv/1498/FotoOrj.jpeg\""
  },
  {
    "Name": "Serdar ÖZDEMİR",
    "Birth Information": "MAZGIRT - 1972",
    "Organization": "PKK/KCK Terör Örgütü",
    "Photo URL": "\"/kurumlar/terorarananlar.pol.tr/Arsiv/53/FotoOrj.jpeg\""
  },
  {
    "Name": "Habip ÇİFTÇİ",
    "Birth Information": "BİTLİS - 1973",
    "Organization": "PKK/KCK Terör Örgütü",
    "Photo URL": "\"/kurumlar/terorarananlar.pol.tr/30-KOMISYON/26-HABIB-CIFTCI.jpg\""
  },
  {
    "Name": "Şerif Ali TEKALAN",
    "Birth Information": "SANDIKLI - 1952",
    "Organization": "FETÖ/PDY Terör Örgütü",
    "Photo URL": "\"/kurumlar/terorarananlar.pol.tr/Arsiv/793/FotoOrj.jpeg\""
  },
  {
    "Name": "Uğur UÇAN",
    "Birth Information": "ISTANBUL - 1981",
    "Organization": "FETÖ/PDY Terör Örgütü",
    "Photo URL": "\"/kurumlar/terorarananlar.pol.tr/Arsiv/1485/FotoOrj.jpeg\""
  },
  {
    "Name": "Abdulcelil YILMAZ",
    "Birth Information": "ERUH - 1973",
    "Organization": "PKK/KCK Terör Örgütü",
    "Photo URL": "\"/kurumlar/terorarananlar.pol.tr/Arsiv/113/FotoOrj.jpeg\""
  },
  {
    "Name": "Mehmet Nail YİĞİT",
    "Birth Information": "FETHIYE - 1968",
    "Organization": "FETÖ/PDY Terör Örgütü",
    "Photo URL": "\"/kurumlar/terorarananlar.pol.tr/Arsiv/1490/FotoOrj.jpeg\""
  },
  {
    "Name": "Kumri KARA",
    "Birth Information": "ULUDERE - 1988",
    "Organization": "PKK/KCK Terör Örgütü",
    "Photo URL": "\"/kurumlar/terorarananlar.pol.tr/30-KOMISYON/11_KUMRI-KARA.jpg\""
  },
  {
    "Name": "Adnan TİTİZ",
    "Birth Information": "ÖZALP - 1982",
    "Organization": "PKK/KCK Terör Örgütü",
    "Photo URL": "\"/kurumlar/terorarananlar.pol.tr/28-KOMISYON/13_ADNAN-TITIZ.jpg\""
  },
  {
    "Name": "Ferudun ÇOBAN",
    "Birth Information": "ARTOVA - 1980",
    "Organization": "FETÖ/PDY Terör Örgütü",
    "Photo URL": "\"/kurumlar/terorarananlar.pol.tr/Arsiv/1484/FotoOrj.jpeg\""
  },
  {
    "Name": "Kamuran YÜKSEK",
    "Birth Information": "KARAYAZI - 1980",
    "Organization": "PKK/KCK Terör Örgütü",
    "Photo URL": "\"/kurumlar/terorarananlar.pol.tr/28-KOMISYON/1_KAMURAN-YUKSEK.jpg\""
  },
  {
    "Name": "Cevher KARA",
    "Birth Information": "ULUDERE - 1985",
    "Organization": "PKK/KCK Terör Örgütü",
    "Photo URL": "\"/kurumlar/terorarananlar.pol.tr/30-KOMISYON/51-CEVHER-KARA.jpg\""
  },
  {
    "Name": "Nazım GÜR",
    "Birth Information": "BEYTÜŞŞEBAP - 1979",
    "Organization": "PKK/KCK Terör Örgütü",
    "Photo URL": "\"/kurumlar/terorarananlar.pol.tr/31KOMISYON/88_NAZIM-GUR.jpg\""
  },
  {
    "Name": "Zeynep YILDIRIM",
    "Birth Information": "HEKIMHAN - 1971",
    "Organization": "PKK/KCK Terör Örgütü",
    "Photo URL": "\"/kurumlar/terorarananlar.pol.tr/Arsiv/1590/FotoOrj.jpeg\""
  },
  {
    "Name": "Hasan KOYUNCU",
    "Birth Information": "GÜRÜN - 1967",
    "Organization": "PKK/KCK Terör Örgütü",
    "Photo URL": "\"/kurumlar/terorarananlar.pol.tr/31KOMISYON/HASAN-KOYUNCU.jpg\""
  },
  {
    "Name": "Cuma GÜLLÜ",
    "Birth Information": "ŞANLIURFA - 1978",
    "Organization": "PKK/KCK Terör Örgütü",
    "Photo URL": "\"/kurumlar/terorarananlar.pol.tr/30-KOMISYON/8_CUMA-GULLU.jpg\""
  },
  {
    "Name": "Turgay SÖKMEN",
    "Birth Information": "ERZINCAN - 1976",
    "Organization": "FETÖ/PDY Terör Örgütü",
    "Photo URL": "\"/kurumlar/terorarananlar.pol.tr/Arsiv/80/FotoOrj.jpeg\""
  },
  {
    "Name": "Ferhat Abdi ŞAHİN",
    "Birth Information": "SURIYE - 1963",
    "Organization": "PKK/KCK Terör Örgütü",
    "Photo URL": "\"/kurumlar/terorarananlar.pol.tr/Arsiv/1045/FotoOrj.jpeg\""
  },
  {
    "Name": "Kemal KUTAN",
    "Birth Information": "TUNCELI - 1965",
    "Organization": "MKP Terör Örgütü",
    "Photo URL": "\"/kurumlar/terorarananlar.pol.tr/Arsiv/85/FotoOrj.jpeg\""
  },
  {
    "Name": "Ali DEMİR",
    "Birth Information": "GERCÜS - 1984",
    "Organization": "PKK/KCK Terör Örgütü",
    "Photo URL": "\"/kurumlar/terorarananlar.pol.tr/Arsiv/222/FotoOrj.jpeg\""
  },
  {
    "Name": "Salman KURTULAN",
    "Birth Information": "PAZARCIK - 1962",
    "Organization": "PKK/KCK Terör Örgütü",
    "Photo URL": "\"/kurumlar/terorarananlar.pol.tr/Arsiv/115/FotoOrj.jpeg\""
  },
  {
    "Name": "Cemal TÜRK",
    "Birth Information": "TURGUTLU - 1964",
    "Organization": "FETÖ/PDY Terör Örgütü",
    "Photo URL": "\"/kurumlar/terorarananlar.pol.tr/Arsiv/185/FotoOrj.jpeg\""
  },
  {
    "Name": "Salih MÜSLÜM",
    "Birth Information": "SURIYE - 1951",
    "Organization": "PKK/KCK Terör Örgütü",
    "Photo URL": "\"/kurumlar/terorarananlar.pol.tr/Arsiv/1046/FotoOrj_1.jpeg\""
  },
  {
    "Name": "DİDEM BOZKAYA",
    "Birth Information": "SURUÇ - 1982",
    "Organization": "PKK/KCK Terör Örgütü",
    "Photo URL": "\"/kurumlar/terorarananlar.pol.tr/33KOMISYON/DIDEM-BOZKAYA.jpg\""
  },
  {
    "Name": "Lokman Abdullah İBRAHİM",
    "Birth Information": "Erbil - 1972",
    "Organization": "PKK/KCK Terör Örgütü",
    "Photo URL": "\"/kurumlar/terorarananlar.pol.tr/Arsiv/1799/FotoOrj.jpeg\""
  },
  {
    "Name": "Turgut KAYA",
    "Birth Information": "MAÇKA - 1973",
    "Organization": "TKP-ML Konferans Terör Örgütü",
    "Photo URL": "\"/kurumlar/terorarananlar.pol.tr/Arsiv/95/FotoOrj.jpeg\""
  },
  {
    "Name": "Yılmaz DAĞLUM",
    "Birth Information": "SİVEREK - 1958",
    "Organization": "PKK/KCK Terör Örgütü",
    "Photo URL": "\"/kurumlar/terorarananlar.pol.tr/28-KOMISYON/12_YILMAZ-DAGLUM.jpg\""
  },
  {
    "Name": "Nulifer KOÇ",
    "Birth Information": "ARDAHAN - 1969",
    "Organization": "PKK/KCK Terör Örgütü",
    "Photo URL": "\"/kurumlar/terorarananlar.pol.tr/Arsiv/1052/FotoOrj.jpeg\""
  },
  {
    "Name": "Ahmed Said TUNÇPİNAR",
    "Birth Information": "BAYBURT - 1974",
    "Organization": "FETÖ/PDY Terör Örgütü",
    "Photo URL": "\"/kurumlar/terorarananlar.pol.tr/31KOMISYON/AHMED-SAID-TUNCPINAR.jpg\""
  },
  {
    "Name": "Ramazan AÇIKYÜZ",
    "Birth Information": "ESKISEHIR - 1976",
    "Organization": "PKK/KCK Terör Örgütü",
    "Photo URL": "\"/kurumlar/terorarananlar.pol.tr/Arsiv/48/FotoOrj.jpeg\""
  },
  {
    "Name": "Asya OSMAN(ABDULLAH)",
    "Birth Information": "HASİÇİ - 1971",
    "Organization": "PKK/KCK Terör Örgütü",
    "Photo URL": "\"/kurumlar/terorarananlar.pol.tr/31KOMISYON/ASYA-ABDULLAH.jpg\""
  },
  {
    "Name": "Gülüşan EKSEN",
    "Birth Information": "SETER - 1965",
    "Organization": "PKK/KCK Terör Örgütü",
    "Photo URL": "\"/kurumlar/terorarananlar.pol.tr/Arsiv/50/FotoOrj_1.jpeg\""
  },
  {
    "Name": "Ayten ATALAY",
    "Birth Information": "DERIK - 1981",
    "Organization": "PKK/KCK Terör Örgütü",
    "Photo URL": "\"/kurumlar/terorarananlar.pol.tr/Arsiv/1242/FotoOrj.jpeg\""
  },
  {
    "Name": "Ömer ÇİFTÇİ",
    "Birth Information": "OSMANİYE - 1980",
    "Organization": "EL KAİDE Terör Örgütü",
    "Photo URL": "\"/kurumlar/terorarananlar.pol.tr/30-KOMISYON/27-OMER-CIFTCI.jpg\""
  },
  {
    "Name": "Ahmet GÜZEL",
    "Birth Information": "BALA - 1977",
    "Organization": "FETÖ/PDY Terör Örgütü",
    "Photo URL": "\"/kurumlar/terorarananlar.pol.tr/Arsiv/1487/FotoOrj.jpeg\""
  },
  {
    "Name": "Ali URSAVAŞ",
    "Birth Information": "INCIRAGACI - 1962",
    "Organization": "FETÖ/PDY Terör Örgütü",
    "Photo URL": "\"/kurumlar/terorarananlar.pol.tr/Arsiv/781/FotoOrj.jpeg\""
  },
  {
    "Name": "Nusret YILMAZ",
    "Birth Information": "BESNI - 1984",
    "Organization": "DEAŞ Terör Örgütü",
    "Photo URL": "\"/kurumlar/terorarananlar.pol.tr/Arsiv/292/FotoOrj_1.jpeg\""
  },
  {
    "Name": "Mahmut DORA",
    "Birth Information": "BIRINI - 1956",
    "Organization": "PKK/KCK Terör Örgütü",
    "Photo URL": "\"/kurumlar/terorarananlar.pol.tr/Arsiv/110/FotoOrj.jpeg\""
  },
  {
    "Name": "Faruk AKALTUN",
    "Birth Information": "ŞANLIURFA - 1972",
    "Organization": "PKK/KCK Terör Örgütü",
    "Photo URL": "\"/kurumlar/terorarananlar.pol.tr/30-KOMISYON/15_FARUK-AKALTUN.jpg\""
  },
  {
    "Name": "Başak Şahin DUMAN",
    "Birth Information": "ANKARA - 1979",
    "Organization": "MLKP Terör Örgütü",
    "Photo URL": "\"/kurumlar/terorarananlar.pol.tr/30-KOMISYON/9_BASAK-SAHIN-DUMAN.jpg\""
  },
  {
    "Name": "Abbas SERTKAYA",
    "Birth Information": "VARTO/İÇMELER - 1974",
    "Organization": "PKK/KCK Terör Örgütü",
    "Photo URL": "\"/kurumlar/terorarananlar.pol.tr/30-KOMISYON/BOS.jpg\""
  },
  {
    "Name": "Fehmi ATALAY",
    "Birth Information": "LICE - 1969",
    "Organization": "PKK/KCK Terör Örgütü",
    "Photo URL": "\"/kurumlar/terorarananlar.pol.tr/Arsiv/103/FotoOrj.jpeg\""
  },
  {
    "Name": "Nevzat AYVACI",
    "Birth Information": "GÜZELSU - 1948",
    "Organization": "FETÖ/PDY Terör Örgütü",
    "Photo URL": "\"/kurumlar/terorarananlar.pol.tr/Arsiv/166/FotoOrj.jpeg\""
  },
  {
    "Name": "Mehmet GÜCİN",
    "Birth Information": "BİNGÖL - 1984",
    "Organization": "PKK/KCK Terör Örgütü",
    "Photo URL": "\"/kurumlar/terorarananlar.pol.tr/30-KOMISYON/42-MEHMET-GUCIN.jpg\""
  },
  {
    "Name": "Seyfi POLAT",
    "Birth Information": "MAZGIRT - 1967",
    "Organization": "MLKP Terör Örgütü",
    "Photo URL": "\"/kurumlar/terorarananlar.pol.tr/Arsiv/88/FotoOrj_1.jpeg\""
  },
  {
    "Name": "Yeşim TURŞAK",
    "Birth Information": "EDREMİT - 1988",
    "Organization": "PKK/KCK Terör Örgütü",
    "Photo URL": "\"/kurumlar/terorarananlar.pol.tr/28-KOMISYON/23_YESIM-TURSAK.jpg\""
  },
  {
    "Name": "Osman ŞEN",
    "Birth Information": "TELBİSİM - 1963",
    "Organization": "PKK/KCK Terör Örgütü",
    "Photo URL": "\"/kurumlar/terorarananlar.pol.tr/28-KOMISYON/5_OSMAN-SEN.jpg\""
  },
  {
    "Name": "Adem UZUN",
    "Birth Information": "KIRSEHIR - 1967",
    "Organization": "PKK/KCK Terör Örgütü",
    "Photo URL": "\"/kurumlar/terorarananlar.pol.tr/Arsiv/16/FotoOrj.jpeg\""
  },
  {
    "Name": "Fatoş YENER",
    "Birth Information": "PAZARCIK - 1968",
    "Organization": "PKK/KCK Terör Örgütü",
    "Photo URL": "\"/kurumlar/terorarananlar.pol.tr/Arsiv/1596/FotoOrj.jpeg\""
  },
  {
    "Name": "Zekeriya YILDIZ",
    "Birth Information": "ERGANİ - 1978",
    "Organization": "PKK/KCK Terör Örgütü",
    "Photo URL": "\"/kurumlar/terorarananlar.pol.tr/31KOMISYON/ZEKERIYA-YILDIZ.jpg\""
  },
  {
    "Name": "Gülseren ÖZDEMİR",
    "Birth Information": "MİDYAT - 1978",
    "Organization": "PKK/KCK Terör Örgütü",
    "Photo URL": "\"/kurumlar/terorarananlar.pol.tr/28-KOMISYON/4_GULSEREN-OZDEMIR.jpg\""
  },
  {
    "Name": "Rıza ALTUN",
    "Birth Information": "K.SÖBEÇIMEN - 1956",
    "Organization": "PKK/KCK Terör Örgütü",
    "Photo URL": "\"/kurumlar/terorarananlar.pol.tr/Arsiv/21/FotoOrj.jpeg\""
  },
  {
    "Name": "Mehmet Erdoğan TÜZÜN",
    "Birth Information": "ISPARTA - 1943",
    "Organization": "FETÖ/PDY Terör Örgütü",
    "Photo URL": "\"/kurumlar/terorarananlar.pol.tr/Arsiv/34/FotoOrj.jpeg\""
  },
  {
    "Name": "Kenan EREN",
    "Birth Information": "ERCIS - 1980",
    "Organization": "PKK/KCK Terör Örgütü",
    "Photo URL": "\"/kurumlar/terorarananlar.pol.tr/Arsiv/315/FotoOrj.jpeg\""
  },
  {
    "Name": "Bergüzar DUMLU",
    "Birth Information": "DOGUBAYAZIT - 1968",
    "Organization": "PKK/KCK Terör Örgütü",
    "Photo URL": "\"/kurumlar/terorarananlar.pol.tr/Arsiv/1592/FotoOrj.jpeg\""
  },
  {
    "Name": "Fatma NARÇİN",
    "Birth Information": "IDIL - 1971",
    "Organization": "PKK/KCK Terör Örgütü",
    "Photo URL": "\"/kurumlar/terorarananlar.pol.tr/Arsiv/1638/FotoOrj.jpeg\""
  },
  {
    "Name": "Rıdvan ALKAN",
    "Birth Information": "PATNOS - 1988",
    "Organization": "PKK/KCK Terör Örgütü",
    "Photo URL": "\"/kurumlar/terorarananlar.pol.tr/Arsiv/1540/FotoOrj.jpeg\""
  },
  {
    "Name": "Yusuf DEMİR",
    "Birth Information": "SANIK - 1957",
    "Organization": "MLKP Terör Örgütü",
    "Photo URL": "\"/kurumlar/terorarananlar.pol.tr/Arsiv/1678/FotoOrj.jpeg\""
  },
  {
    "Name": "Emine MANTU",
    "Birth Information": "IZMIR - 1977",
    "Organization": "PKK/KCK Terör Örgütü",
    "Photo URL": "\"/kurumlar/terorarananlar.pol.tr/Arsiv/1060/FotoOrj.jpeg\""
  },
  {
    "Name": "Necla ORHAN",
    "Birth Information": "NUSAYBIN - 1972",
    "Organization": "PKK/KCK Terör Örgütü",
    "Photo URL": "\"/kurumlar/terorarananlar.pol.tr/Arsiv/65/FotoOrj_1.jpeg\""
  },
  {
    "Name": "Remzi KARTAL",
    "Birth Information": "VAN - 1948",
    "Organization": "PKK/KCK Terör Örgütü",
    "Photo URL": "\"/kurumlar/terorarananlar.pol.tr/Arsiv/18/FotoOrj.jpeg\""
  },
  {
    "Name": "Gönül TEPE",
    "Birth Information": "DELIKAN - 1959",
    "Organization": "PKK/KCK Terör Örgütü",
    "Photo URL": "\"/kurumlar/terorarananlar.pol.tr/Arsiv/108/FotoOrj.jpeg\""
  },
  {
    "Name": "ZÜLFÜNAZ COŞKUN",
    "Birth Information": "KARAKOÇAN - 1979",
    "Organization": "PKK/KCK Terör Örgütü",
    "Photo URL": "\"/kurumlar/terorarananlar.pol.tr/33KOMISYON/ZULFUNAZ-COSKUN.jpg\""
  },
  {
    "Name": "Gül ZEREN",
    "Birth Information": "ALACAKAYA - 1993",
    "Organization": "PKK/KCK Terör Örgütü",
    "Photo URL": "\"/kurumlar/terorarananlar.pol.tr/30-KOMISYON/47-GUL-ZEREN.jpg\""
  },
  {
    "Name": "Ali NOVRUZI",
    "Birth Information": "IRAN - 1980",
    "Organization": "PKK/KCK Terör Örgütü",
    "Photo URL": "\"/kurumlar/terorarananlar.pol.tr/Arsiv/1797/FotoOrj.jpeg\""
  },
  {
    "Name": "Hüseyin KARA",
    "Birth Information": "GÜNEYCE - 1953",
    "Organization": "FETÖ/PDY Terör Örgütü",
    "Photo URL": "\"/kurumlar/terorarananlar.pol.tr/Arsiv/191/FotoOrj.jpeg\""
  },
  {
    "Name": "Abdulkadir ZENGER",
    "Birth Information": "HILVAN - 1971",
    "Organization": "PKK/KCK Terör Örgütü",
    "Photo URL": "\"/kurumlar/terorarananlar.pol.tr/Arsiv/107/FotoOrj_1.jpeg\""
  },
  {
    "Name": "Muzaffer AYATA",
    "Birth Information": "SIVEREK - 1956",
    "Organization": "PKK/KCK Terör Örgütü",
    "Photo URL": "\"/kurumlar/terorarananlar.pol.tr/Arsiv/14/FotoOrj.jpeg\""
  },
  {
    "Name": "Musa AŞOĞLU",
    "Birth Information": "HENDEK - 1961",
    "Organization": "DHKP/C Terör Örgütü",
    "Photo URL": "\"/kurumlar/terorarananlar.pol.tr/Arsiv/23/FotoOrj_1.jpeg\""
  },
  {
    "Name": "Recep BALTACI",
    "Birth Information": "SEYHAN - 1995",
    "Organization": "EL KAİDE Terör Örgütü",
    "Photo URL": "\"/kurumlar/terorarananlar.pol.tr/Arsiv/1628/FotoOrj.jpeg\""
  },
  {
    "Name": "Azime KARA",
    "Birth Information": "ULUDERE - 1977",
    "Organization": "PKK/KCK Terör Örgütü",
    "Photo URL": "\"/kurumlar/terorarananlar.pol.tr/Arsiv/428/FotoOrj.jpeg\""
  },
  {
    "Name": "Elham AHMED",
    "Birth Information": "HALEP - 1972",
    "Organization": "PKK/KCK Terör Örgütü",
    "Photo URL": "\"/kurumlar/terorarananlar.pol.tr/31KOMISYON/ELHAM-AMHED.jpg\""
  },
  {
    "Name": "Mehmet Fatih GÖGERCİN",
    "Birth Information": "HANI - 1983",
    "Organization": "DEAŞ Terör Örgütü",
    "Photo URL": "\"/kurumlar/terorarananlar.pol.tr/Arsiv/1626/FotoOrj.jpeg\""
  },
  {
    "Name": "Arjin BAYSAL",
    "Birth Information": "DARGEÇİT - 1992",
    "Organization": "PKK/KCK Terör Örgütü",
    "Photo URL": "\"/kurumlar/terorarananlar.pol.tr/28-KOMISYON/25_ARJIN-BAYSAL.jpg\""
  },
  {
    "Name": "İbrahim ÇİÇEK",
    "Birth Information": "DIVRIGI - 1956",
    "Organization": "MLKP Terör Örgütü",
    "Photo URL": "\"/kurumlar/terorarananlar.pol.tr/Arsiv/92/FotoOrj_1.jpeg\""
  },
  {
    "Name": "Muhammed YEŞİLYURT",
    "Birth Information": "SALIPAZARI - 1988",
    "Organization": "FETÖ/PDY Terör Örgütü",
    "Photo URL": "\"/kurumlar/terorarananlar.pol.tr/31KOMISYON/MUHAMMED-YESILYURT.jpg\""
  },
  {
    "Name": "Mehmet Emin ATEŞ",
    "Birth Information": "KULP - 1980",
    "Organization": "PKK/KCK Terör Örgütü",
    "Photo URL": "\"/kurumlar/terorarananlar.pol.tr/MEHMET-EMIN-ATES.jpg\""
  },
  {
    "Name": "Nurullah ALBAYRAK",
    "Birth Information": "ANKARA - 1973",
    "Organization": "FETÖ/PDY Terör Örgütü",
    "Photo URL": "\"/kurumlar/terorarananlar.pol.tr/31KOMISYON/NURULLAH-ALBAYRAK.jpg\""
  },
  {
    "Name": "Süleyman GÜNYELİ",
    "Birth Information": "GEDNE - 1957",
    "Organization": "PKK/KCK Terör Örgütü",
    "Photo URL": "\"/kurumlar/terorarananlar.pol.tr/Arsiv/1597/FotoOrj.jpeg\""
  },
  {
    "Name": "Muaz Bin Cebel GÜLEN",
    "Birth Information": "ERZURUM - 1975",
    "Organization": "FETÖ/PDY Terör Örgütü",
    "Photo URL": "\"/kurumlar/terorarananlar.pol.tr/31KOMISYON/MUAZ-BIN-CEBEL.jpg\""
  },
  {
    "Name": "Mehmet GÜNEŞ",
    "Birth Information": "ZARA - 1951",
    "Organization": "DKP/BÖG Terör Örgütü",
    "Photo URL": "\"/kurumlar/terorarananlar.pol.tr/Arsiv/266/FotoOrj_1.jpeg\""
  },
  {
    "Name": "Cemal ŞERİK",
    "Birth Information": "DIVRIGI - 1962",
    "Organization": "PKK/KCK Terör Örgütü",
    "Photo URL": "\"/kurumlar/terorarananlar.pol.tr/Arsiv/51/FotoOrj_1.jpeg\""
  },
  {
    "Name": "Şükran SADAY",
    "Birth Information": "NUSAYBIN - 1976",
    "Organization": "PKK/KCK Terör Örgütü",
    "Photo URL": "\"/kurumlar/terorarananlar.pol.tr/Arsiv/58/FotoOrj.jpeg\""
  },
  {
    "Name": "Emine ARAR",
    "Birth Information": "YÜKSEKOVA - 1985",
    "Organization": "PKK/KCK Terör Örgütü",
    "Photo URL": "\"/kurumlar/terorarananlar.pol.tr/31KOMISYON/89_EMINE-ARAR.jpg\""
  },
  {
    "Name": "Eşrefedip AYDIN",
    "Birth Information": "ÇUKURCA - 1973",
    "Organization": "PKK/KCK Terör Örgütü",
    "Photo URL": "\"/kurumlar/terorarananlar.pol.tr/Arsiv/196/FotoOrj_1.jpeg\""
  },
  {
    "Name": "Ender BUDANCER",
    "Birth Information": "MALAZGIRT - 1980",
    "Organization": "PKK/KCK Terör Örgütü",
    "Photo URL": "\"/kurumlar/terorarananlar.pol.tr/Arsiv/329/FotoOrj.jpeg\""
  },
  {
    "Name": "Faruk ERDEMİR",
    "Birth Information": "ÇUKURCA - 1973",
    "Organization": "PKK/KCK Terör Örgütü",
    "Photo URL": "\"/kurumlar/terorarananlar.pol.tr/Arsiv/116/FotoOrj.jpeg\""
  },
  {
    "Name": "CEVAHİR YANAR",
    "Birth Information": "GENÇ - 1972",
    "Organization": "PKK/KCK Terör Örgütü",
    "Photo URL": "\"/kurumlar/terorarananlar.pol.tr/33KOMISYON/CEVAHIR-YANAR.jpg\""
  },
  {
    "Name": "Serpil ARSLAN",
    "Birth Information": "BULANIK - 1974",
    "Organization": "MLKP Terör Örgütü",
    "Photo URL": "\"/kurumlar/terorarananlar.pol.tr/Arsiv/1676/FotoOrj.jpeg\""
  },
  {
    "Name": "Emine TEKAS",
    "Birth Information": "SILOPI - 1974",
    "Organization": "PKK/KCK Terör Örgütü",
    "Photo URL": "\"/kurumlar/terorarananlar.pol.tr/Arsiv/1543/FotoOrj.jpeg\""
  },
  {
    "Name": "Mehmet Cudi SEZGİN",
    "Birth Information": "NUSAYBİN - 1993",
    "Organization": "PKK/KCK Terör Örgütü",
    "Photo URL": "\"/kurumlar/terorarananlar.pol.tr/30-KOMISYON/43-MEHMET-CUDI-SEZGIN.jpg\""
  },
  {
    "Name": "Ahmet Zeki GEREHAN",
    "Birth Information": "ESKISEHIR - 1972",
    "Organization": "FETÖ/PDY Terör Örgütü",
    "Photo URL": "\"/kurumlar/terorarananlar.pol.tr/Arsiv/1489/FotoOrj.jpeg\""
  },
  {
    "Name": "Gülbahar KÖKER",
    "Birth Information": "ELBİSTAN - 1975",
    "Organization": "PKK/KCK Terör Örgütü",
    "Photo URL": "\"/kurumlar/terorarananlar.pol.tr/Gulbahar-KOKER.png\""
  },
  {
    "Name": "Neval HAMİTOĞLU",
    "Birth Information": "MAZIDAGI - 1979",
    "Organization": "PKK/KCK Terör Örgütü",
    "Photo URL": "\"/kurumlar/terorarananlar.pol.tr/Arsiv/1053/FotoOrj.jpeg\""
  },
  {
    "Name": "Ali BENEK",
    "Birth Information": "ULUDERE - 1958",
    "Organization": "PKK/KCK Terör Örgütü",
    "Photo URL": "\"/kurumlar/terorarananlar.pol.tr/Arsiv/1050/FotoOrj.jpeg\""
  },
  {
    "Name": "AHMET KARAMUS",
    "Birth Information": "YENKİCE - 1961",
    "Organization": "PKK/KCK Terör Örgütü",
    "Photo URL": "\"/kurumlar/terorarananlar.pol.tr/33KOMISYON/AHMET-KALAMUS.jpg\""
  },
  {
    "Name": "Harun TOKAK",
    "Birth Information": "USAK - 1955",
    "Organization": "FETÖ/PDY Terör Örgütü",
    "Photo URL": "\"/kurumlar/terorarananlar.pol.tr/Arsiv/247/FotoOrj.jpeg\""
  },
  {
    "Name": "Eyyüp DORU",
    "Birth Information": "IGDIR - 1960",
    "Organization": "PKK/KCK Terör Örgütü",
    "Photo URL": "\"/kurumlar/terorarananlar.pol.tr/Arsiv/1598/FotoOrj.jpeg\""
  },
  {
    "Name": "Rahşan AKSOY",
    "Birth Information": "GÖLYAZI - 1976",
    "Organization": "PKK/KCK Terör Örgütü",
    "Photo URL": "\"/kurumlar/terorarananlar.pol.tr/30-KOMISYON/24-RAHSAN-AKSOY.jpg\""
  },
  {
    "Name": "Zozan ÇETİN",
    "Birth Information": "HAKKARI - 1992",
    "Organization": "PKK/KCK Terör Örgütü",
    "Photo URL": "\"/kurumlar/terorarananlar.pol.tr/Arsiv/680/FotoOrj.jpeg\""
  },
  {
    "Name": "Cemal ELDEMİR",
    "Birth Information": "AKARSU - 1974",
    "Organization": "PKK/KCK Terör Örgütü",
    "Photo URL": "\"/kurumlar/terorarananlar.pol.tr/30-KOMISYON/19-CEMAL-ELDEMIR.jpg\""
  },
  {
    "Name": "Mehmet TÖREN",
    "Birth Information": "BOZOVA - 1962",
    "Organization": "PKK/KCK Terör Örgütü",
    "Photo URL": "\"/kurumlar/terorarananlar.pol.tr/Arsiv/15/FotoOrj.jpeg\""
  },
  {
    "Name": "Yılmaz YİĞİT",
    "Birth Information": "TUNÇBİLEK - 1965",
    "Organization": "FETÖ/PDY Terör Örgütü",
    "Photo URL": "\"/kurumlar/terorarananlar.pol.tr/31KOMISYON/YILMAZ-YIGIT.jpg\""
  },
  {
    "Name": "Remzi AVCI",
    "Birth Information": "KULP - 1977",
    "Organization": "PKK/KCK Terör Örgütü",
    "Photo URL": "\"/kurumlar/terorarananlar.pol.tr/31KOMISYON/REMZI-AVCI.jpg\""
  },
  {
    "Name": "Sultan KOCABEY",
    "Birth Information": "ERKENT - 1975",
    "Organization": "PKK/KCK Terör Örgütü",
    "Photo URL": "\"/kurumlar/terorarananlar.pol.tr/Arsiv/69/FotoOrj_1.jpeg\""
  },
  {
    "Name": "Reşit HAYLAMAZ",
    "Birth Information": "AVLAGIÇAYIRI - 1965",
    "Organization": "FETÖ/PDY Terör Örgütü",
    "Photo URL": "\"/kurumlar/terorarananlar.pol.tr/Arsiv/187/FotoOrj.jpeg\""
  },
  {
    "Name": "Mustafa GÜNEŞ",
    "Birth Information": "AFSIN - 1970",
    "Organization": "DEAŞ Terör Örgütü",
    "Photo URL": "\"/kurumlar/terorarananlar.pol.tr/Arsiv/277/FotoOrj_1.jpeg\""
  },
  {
    "Name": "Havva ERGÜN",
    "Birth Information": "DIYARBAKIR - 1998",
    "Organization": "PKK/KCK Terör Örgütü",
    "Photo URL": "\"/kurumlar/terorarananlar.pol.tr/Arsiv/1693/FotoOrj.jpeg\""
  },
  {
    "Name": "Abdulgafur DİNÇ",
    "Birth Information": "YÜKSEKOVA - 1975",
    "Organization": "PKK/KCK Terör Örgütü",
    "Photo URL": "\"/kurumlar/terorarananlar.pol.tr/ABDULGAFUR-DINC.jpg\""
  },
  {
    "Name": "Serdar KAYA",
    "Birth Information": "ISTANBUL - 1955",
    "Organization": "DEVRİMCİ KARARGAH Terör Örgütü",
    "Photo URL": "\"/kurumlar/terorarananlar.pol.tr/Arsiv/44/FotoOrj_1.jpeg\""
  },
  {
    "Name": "Yaşar ÇEKİK",
    "Birth Information": "YÜKSEKOVA - 1977",
    "Organization": "PKK/KCK Terör Örgütü",
    "Photo URL": "\"/kurumlar/terorarananlar.pol.tr/31KOMISYON/YASAR-CELIK.jpg\""
  },
  {
    "Name": "Elif MUHAMMED",
    "Birth Information": "null - null",
    "Organization": "PKK/KCK Terör Örgütü",
    "Photo URL": "\"/kurumlar/terorarananlar.pol.tr/36_KOMISYON/ELIF-MUHAMMED.jpg\""
  },
  {
    "Name": "Faik OĞAÇ",
    "Birth Information": "HİLVAN - 1973",
    "Organization": "PKK/KCK Terör Örgütü",
    "Photo URL": "\"/kurumlar/terorarananlar.pol.tr/31KOMISYON/99_FAIK-OGAC.jpg\""
  },
  {
    "Name": "Türkan ÇETİN",
    "Birth Information": "HIZAN - 1976",
    "Organization": "PKK/KCK Terör Örgütü",
    "Photo URL": "\"/kurumlar/terorarananlar.pol.tr/Arsiv/174/FotoOrj_1.jpeg\""
  },
  {
    "Name": "Adem KALAÇ",
    "Birth Information": "BUCA - 1964",
    "Organization": "FETÖ/PDY Terör Örgütü",
    "Photo URL": "\"/kurumlar/terorarananlar.pol.tr/31KOMISYON/ADEM-KALAC.jpg\""
  },
  {
    "Name": "Cemil BAYIK",
    "Birth Information": "ASAGIÇAKMAK - 1955",
    "Organization": "PKK/KCK Terör Örgütü",
    "Photo URL": "\"/kurumlar/terorarananlar.pol.tr/Arsiv/1/FotoOrj.jpeg\""
  },
  {
    "Name": "Lokman KATMIŞ",
    "Birth Information": "TARSUS - 1993",
    "Organization": "PKK/KCK Terör Örgütü",
    "Photo URL": "\"/kurumlar/terorarananlar.pol.tr/30-KOMISYON/63-LOKMAN-KATMIS.jpg\""
  },
  {
    "Name": "Mustafa DAŞDEMİR",
    "Birth Information": "BULANIK - 1973",
    "Organization": "PKK/KCK Terör Örgütü",
    "Photo URL": "\"/kurumlar/terorarananlar.pol.tr/Arsiv/1639/FotoOrj.jpeg\""
  },
  {
    "Name": "Saniye KUTLU",
    "Birth Information": "ŞIRNAK - 1985",
    "Organization": "PKK/KCK Terör Örgütü",
    "Photo URL": "\"/kurumlar/terorarananlar.pol.tr/SANIYE-KUTLU.jpg\""
  },
  {
    "Name": "Nurcan AĞRALİ",
    "Birth Information": "YÜKSEKOVA - 1985",
    "Organization": "PKK/KCK Terör Örgütü",
    "Photo URL": "\"/kurumlar/terorarananlar.pol.tr/31KOMISYON/Nurcan-AGRALI.jpg\""
  },
  {
    "Name": "Mehmet Tahir KILIÇ",
    "Birth Information": "B.KINER - 1966",
    "Organization": "PKK/KCK Terör Örgütü",
    "Photo URL": "\"/kurumlar/terorarananlar.pol.tr/Arsiv/98/FotoOrj.jpeg\""
  },
  {
    "Name": "Veysel SEVİNÇ",
    "Birth Information": "PATNOS - 1984",
    "Organization": "PKK/KCK Terör Örgütü",
    "Photo URL": "\"/kurumlar/terorarananlar.pol.tr/Arsiv/1139/FotoOrj.jpeg\""
  },
  {
    "Name": "Osman ÇİÇEK",
    "Birth Information": "BOZOVA - 1977",
    "Organization": "PKK/KCK Terör Örgütü",
    "Photo URL": "\"/kurumlar/terorarananlar.pol.tr/Arsiv/325/FotoOrj.jpeg\""
  },
  {
    "Name": "Sercan ERKOL",
    "Birth Information": "VAN - 1991",
    "Organization": "PKK/KCK Terör Örgütü",
    "Photo URL": "\"/kurumlar/terorarananlar.pol.tr/36_KOMISYON/SERCAN-ERKOL.jpg\""
  },
  {
    "Name": "Arif ÇELEBİ",
    "Birth Information": "ISTANBUL - 1963",
    "Organization": "MLKP Terör Örgütü",
    "Photo URL": "\"/kurumlar/terorarananlar.pol.tr/Arsiv/841/FotoOrj.jpeg\""
  },
  {
    "Name": "Mustafa KARASU",
    "Birth Information": "KARAPINAR - 1950",
    "Organization": "PKK/KCK Terör Örgütü",
    "Photo URL": "\"/kurumlar/terorarananlar.pol.tr/Arsiv/3/FotoOrj.jpeg\""
  },
  {
    "Name": "Mehmet KEREM",
    "Birth Information": "OVACIK - 1978",
    "Organization": "MKP Terör Örgütü",
    "Photo URL": "\"/kurumlar/terorarananlar.pol.tr/Arsiv/41/FotoOrj.jpeg\""
  },
  {
    "Name": "Ramazan KESER",
    "Birth Information": "ADİLCEVAZ - 1992",
    "Organization": "PKK/KCK Terör Örgütü",
    "Photo URL": "\"/kurumlar/terorarananlar.pol.tr/31KOMISYON/RAMAZAN-KESER.jpg\""
  },
  {
    "Name": "Engin KARAASLAN",
    "Birth Information": "KARTALDERE - 1964",
    "Organization": "PKK/KCK Terör Örgütü",
    "Photo URL": "\"/kurumlar/terorarananlar.pol.tr/Arsiv/8/FotoOrj.jpeg\""
  },
  {
    "Name": "Ebuzeyid SAKCAK",
    "Birth Information": "CIZRE - 1970",
    "Organization": "PKK/KCK Terör Örgütü",
    "Photo URL": "\"/kurumlar/terorarananlar.pol.tr/Arsiv/120/FotoOrj.jpeg\""
  },
  {
    "Name": "İlyas DİLSİZ",
    "Birth Information": "ADIYAMAN - 1979",
    "Organization": "PKK/KCK Terör Örgütü",
    "Photo URL": "\"/kurumlar/terorarananlar.pol.tr/31KOMISYON/ILYAS-DILSIZ.jpg\""
  },
  {
    "Name": "Birgül AYAZ",
    "Birth Information": "DIYARBAKIR - 1978",
    "Organization": "PKK/KCK Terör Örgütü",
    "Photo URL": "\"/kurumlar/terorarananlar.pol.tr/Arsiv/121/FotoOrj.jpeg\""
  },
  {
    "Name": "Mehmet Ferdi ELALMIŞ",
    "Birth Information": "YUKARIOCAK - 1982",
    "Organization": "PKK/KCK Terör Örgütü",
    "Photo URL": "\"/kurumlar/terorarananlar.pol.tr/Arsiv/432/FotoOrj.jpeg\""
  },
  {
    "Name": "Saliha BİŞKİN",
    "Birth Information": "NUSAYBIN - 1976",
    "Organization": "PKK/KCK Terör Örgütü",
    "Photo URL": "\"/kurumlar/terorarananlar.pol.tr/Arsiv/615/FotoOrj.jpeg\""
  },
  {
    "Name": "Gazi ÖZDEMİR",
    "Birth Information": "MAZGİRT - 1969",
    "Organization": "PKK/KCK Terör Örgütü",
    "Photo URL": "\"/kurumlar/terorarananlar.pol.tr/30-KOMISYON/23-GAZI-OZDEMIR.jpg\""
  },
  {
    "Name": "Sabri OK",
    "Birth Information": "ADIYAMAN - 1958",
    "Organization": "PKK/KCK Terör Örgütü",
    "Photo URL": "\"/kurumlar/terorarananlar.pol.tr/Arsiv/7/FotoOrj.jpeg\""
  },
  {
    "Name": "Emir Settar MEVLÜT",
    "Birth Information": "SURİYE - 1970",
    "Organization": "PKK/KCK Terör Örgütü",
    "Photo URL": "\"/kurumlar/terorarananlar.pol.tr/28-KOMISYON/14_EMIR-SETTAR-MEVLUT.jpg\""
  },
  {
    "Name": "Zabit İLTÜMÜR",
    "Birth Information": "PERTEK - 1954",
    "Organization": "MLKP Terör Örgütü",
    "Photo URL": "\"/kurumlar/terorarananlar.pol.tr/Arsiv/25/FotoOrj.jpeg\""
  },
  {
    "Name": "Ali Hıdır POLAT",
    "Birth Information": "PÜLÜMÜR - 1960",
    "Organization": "MLKP Terör Örgütü",
    "Photo URL": "\"/kurumlar/terorarananlar.pol.tr/Arsiv/91/FotoOrj.jpeg\""
  },
  {
    "Name": "Gülnaz KULCÜR",
    "Birth Information": "KURTALAN - 1976",
    "Organization": "PKK/KCK Terör Örgütü",
    "Photo URL": "\"/kurumlar/terorarananlar.pol.tr/GULNAZ-KULCUR.jpg\""
  },
  {
    "Name": "Ali Rıza DERMANLI",
    "Birth Information": "OVACIK - 1969",
    "Organization": "MKP Terör Örgütü",
    "Photo URL": "\"/kurumlar/terorarananlar.pol.tr/Arsiv/86/FotoOrj.jpeg\""
  },
  {
    "Name": "Emine GÖK",
    "Birth Information": "BEYTÜSSEBAB - 1978",
    "Organization": "PKK/KCK Terör Örgütü",
    "Photo URL": "\"/kurumlar/terorarananlar.pol.tr/Arsiv/66/FotoOrj.jpeg\""
  },
  {
    "Name": "Muazzez VURAN",
    "Birth Information": "LICE - 1974",
    "Organization": "PKK/KCK Terör Örgütü",
    "Photo URL": "\"/kurumlar/terorarananlar.pol.tr/Arsiv/269/FotoOrj.jpeg\""
  },
  {
    "Name": "Kudret ÜNAL",
    "Birth Information": "SEREFLIKOÇHISAR - 1948",
    "Organization": "FETÖ/PDY Terör Örgütü",
    "Photo URL": "\"/kurumlar/terorarananlar.pol.tr/Arsiv/280/FotoOrj.jpeg\""
  },
  {
    "Name": "Kamile ACAR",
    "Birth Information": "İDİL - 1978",
    "Organization": "PKK/KCK Terör Örgütü",
    "Photo URL": "\"/kurumlar/terorarananlar.pol.tr/28-KOMISYON/3_KAMILE-ACAR.jpg\""
  },
  {
    "Name": "İsa ALTSOY",
    "Birth Information": "BOGAZKÖY - 1961",
    "Organization": "HİZBULLAH Terör Örgütü",
    "Photo URL": "\"/kurumlar/terorarananlar.pol.tr/Arsiv/132/FotoOrj_1.jpeg\""
  },
  {
    "Name": "Naci TOSUN",
    "Birth Information": "KOZANLI - 1950",
    "Organization": "FETÖ/PDY Terör Örgütü",
    "Photo URL": "\"/kurumlar/terorarananlar.pol.tr/Arsiv/36/FotoOrj.jpeg\""
  },
  {
    "Name": "Çiçek TUNÇ",
    "Birth Information": "TAŞLIÇAY - 1991",
    "Organization": "PKK/KCK Terör Örgütü",
    "Photo URL": "\"/kurumlar/terorarananlar.pol.tr/30-KOMISYON/55-CICEK-TUNC.jpg\""
  },
  {
    "Name": "Nuri DUMAN",
    "Birth Information": "HAKKARİ - 1987",
    "Organization": "PKK/KCK Terör Örgütü",
    "Photo URL": "\"/kurumlar/terorarananlar.pol.tr/30-KOMISYON/12_NURI-DUMAN.jpg\""
  },
  {
    "Name": "Duran KALKAN",
    "Birth Information": "MAGARA - 1954",
    "Organization": "PKK/KCK Terör Örgütü",
    "Photo URL": "\"/kurumlar/terorarananlar.pol.tr/Arsiv/6/FotoOrj.jpeg\""
  },
  {
    "Name": "Esma BİLMEZ",
    "Birth Information": "ÇINAR - 1973",
    "Organization": "PKK/KCK Terör Örgütü",
    "Photo URL": "\"/kurumlar/terorarananlar.pol.tr/28-KOMISYON/10_ESMA-BILMEZ.jpg\""
  },
  {
    "Name": "Ufuk GÖLLÜ",
    "Birth Information": "MANAVGAT - 1983",
    "Organization": "DKP/BÖG Terör Örgütü",
    "Photo URL": "\"/kurumlar/terorarananlar.pol.tr/Arsiv/1662/FotoOrj.jpeg\""
  },
  {
    "Name": "Fetullah GÜLEN",
    "Birth Information": "HASANKALE - 1941",
    "Organization": "FETÖ/PDY Terör Örgütü",
    "Photo URL": "\"/kurumlar/terorarananlar.pol.tr/Arsiv/27/FotoOrj.jpeg\""
  },
  {
    "Name": "Ali  DEMİREL",
    "Birth Information": "İSTANBUL - 1974",
    "Organization": "FETÖ/PDY Terör Örgütü",
    "Photo URL": "\"/kurumlar/terorarananlar.pol.tr/31KOMISYON/568_-ALI-DEMIREL.jpg\""
  },
  {
    "Name": "Nuriye KESBİR",
    "Birth Information": "BESIRI - 1961",
    "Organization": "PKK/KCK Terör Örgütü",
    "Photo URL": "\"/kurumlar/terorarananlar.pol.tr/Arsiv/5/FotoOrj.jpeg\""
  },
  {
    "Name": "Cumhur KORKMAZ",
    "Birth Information": "YÜKSEKOVA - 1983",
    "Organization": "PKK/KCK Terör Örgütü",
    "Photo URL": "\"/kurumlar/terorarananlar.pol.tr/Arsiv/1632/FotoOrj.jpeg\""
  },
  {
    "Name": "Nadir YILDIRIM",
    "Birth Information": "HAMUR - 1981",
    "Organization": "PKK/KCK Terör Örgütü",
    "Photo URL": "\"/kurumlar/terorarananlar.pol.tr/28-KOMISYON/2_NADIR-YILDIRIM.jpg\""
  },
  {
    "Name": "Haskar ŞAHİN",
    "Birth Information": "KARAKOÇAN - 1998",
    "Organization": "PKK/KCK Terör Örgütü",
    "Photo URL": "\"/kurumlar/terorarananlar.pol.tr/28-KOMISYON/29_HASKAR-SAHIN.jpg\""
  },
  {
    "Name": "Kadriye SAYIN",
    "Birth Information": "DİGOR - 1969",
    "Organization": "PKK/KCK Terör Örgütü",
    "Photo URL": "\"/kurumlar/terorarananlar.pol.tr/KADRIYE-SAYIN.jpg\""
  },
  {
    "Name": "Fehman HÜSEYİN",
    "Birth Information": "SURIYE - 1969",
    "Organization": "PKK/KCK Terör Örgütü",
    "Photo URL": "\"/kurumlar/terorarananlar.pol.tr/Arsiv/1044/FotoOrj.jpeg\""
  },
  {
    "Name": "Nedim SEVEN",
    "Birth Information": "HAKKARI - 1968",
    "Organization": "PKK/KCK Terör Örgütü",
    "Photo URL": "\"/kurumlar/terorarananlar.pol.tr/Arsiv/139/FotoOrj.jpeg\""
  },
  {
    "Name": "İlhami BALI",
    "Birth Information": "TABUK - 1982",
    "Organization": "DEAŞ Terör Örgütü",
    "Photo URL": "\"/kurumlar/terorarananlar.pol.tr/Arsiv/22/FotoOrj_1.jpeg\""
  },
  {
    "Name": "İsmail NAZLI",
    "Birth Information": "KÜTAHYA - 1974",
    "Organization": "FETÖ/PDY Terör Örgütü",
    "Photo URL": "\"/kurumlar/terorarananlar.pol.tr/Arsiv/1466/FotoOrj.jpeg\""
  },
  {
    "Name": "Bahattin KARATAŞ",
    "Birth Information": "SANLIURFA - 1953",
    "Organization": "FETÖ/PDY Terör Örgütü",
    "Photo URL": "\"/kurumlar/terorarananlar.pol.tr/Arsiv/190/FotoOrj.jpeg\""
  },
  {
    "Name": "Ahmet KARA",
    "Birth Information": "DENIZLI - 1958",
    "Organization": "FETÖ/PDY Terör Örgütü",
    "Photo URL": "\"/kurumlar/terorarananlar.pol.tr/Arsiv/31/FotoOrj.jpeg\""
  },
  {
    "Name": "Songül SICAKYÜZ",
    "Birth Information": "GENÇ - 1990",
    "Organization": "PKK/KCK Terör Örgütü",
    "Photo URL": "\"/kurumlar/terorarananlar.pol.tr/30-KOMISYON/45-SONGUL-SICAKYUZ.jpg\""
  },
  {
    "Name": "Zeynep KARABOĞA",
    "Birth Information": "BAKIRKÖY - 1992",
    "Organization": "MKP Terör Örgütü",
    "Photo URL": "\"/kurumlar/terorarananlar.pol.tr/Arsiv/1687/FotoOrj.jpeg\""
  },
  {
    "Name": "MUSTAFA SARIKAYA",
    "Birth Information": "BABAHAT - 1965",
    "Organization": "PKK/KCK Terör Örgütü",
    "Photo URL": "\"/kurumlar/terorarananlar.pol.tr/33KOMISYON/MUSTAFA-SARIKAYA.jpg\""
  },
  {
    "Name": "Aysel YILDIRIM",
    "Birth Information": "AKÇADAG - 1975",
    "Organization": "DKP/BÖG Terör Örgütü",
    "Photo URL": "\"/kurumlar/terorarananlar.pol.tr/Arsiv/1661/FotoOrj.jpeg\""
  },
  {
    "Name": "Devran YÜRÜK",
    "Birth Information": "ULUDERE - 1993",
    "Organization": "PKK/KCK Terör Örgütü",
    "Photo URL": "\"/kurumlar/terorarananlar.pol.tr/36_KOMISYON/DEVRAN-YURUK.jpg\""
  },
  {
    "Name": "Menice TAŞAN",
    "Birth Information": "DORUK - 1972",
    "Organization": "PKK/KCK Terör Örgütü",
    "Photo URL": "\"/kurumlar/terorarananlar.pol.tr/Arsiv/64/FotoOrj_1.jpeg\""
  },
  {
    "Name": "Yeter İNCE",
    "Birth Information": "OVACIK - 1974",
    "Organization": "PKK/KCK Terör Örgütü",
    "Photo URL": "\"/kurumlar/terorarananlar.pol.tr/Arsiv/1539/FotoOrj.jpeg\""
  },
  {
    "Name": "Mehmet ERGENE",
    "Birth Information": "SERGEN - 1963",
    "Organization": "FETÖ/PDY Terör Örgütü",
    "Photo URL": "\"/kurumlar/terorarananlar.pol.tr/31KOMISYON/MEHMET-ERGENE.jpg\""
  },
  {
    "Name": "Vedat AKBAY",
    "Birth Information": "TATVAN - 1988",
    "Organization": "PKK/KCK Terör Örgütü",
    "Photo URL": "\"/kurumlar/terorarananlar.pol.tr/31KOMISYON/103-VEDAT-AKBAY.jpg\""
  },
  {
    "Name": "Felek DEMİR",
    "Birth Information": "MİDYAT - 1975",
    "Organization": "PKK/KCK Terör Örgütü",
    "Photo URL": "\"/kurumlar/terorarananlar.pol.tr/FELEK-DEMIR.jpg\""
  },
  {
    "Name": "Ramazan AYBİ",
    "Birth Information": "SİLOPİ - 1976",
    "Organization": "PKK/KCK Terör Örgütü",
    "Photo URL": "\"/kurumlar/terorarananlar.pol.tr/28-KOMISYON/15_RAMAZAN-AYBI.jpg\""
  },
  {
    "Name": "Talip BÜYÜK",
    "Birth Information": "ÇAYKARA - 1968",
    "Organization": "FETÖ/PDY Terör Örgütü",
    "Photo URL": "\"/kurumlar/terorarananlar.pol.tr/Arsiv/794/FotoOrj.jpeg\""
  },
  {
    "Name": "Sekvan BABAT",
    "Birth Information": "ULUDERE - 1983",
    "Organization": "PKK/KCK Terör Örgütü",
    "Photo URL": "\"/kurumlar/terorarananlar.pol.tr/31KOMISYON/SEKVAN-BABAT.jpg\""
  },
  {
    "Name": "Ulaş ARSLAN",
    "Birth Information": "SASON - 1975",
    "Organization": "PKK/KCK Terör Örgütü",
    "Photo URL": "\"/kurumlar/terorarananlar.pol.tr/Arsiv/1642/FotoOrj.jpeg\""
  },
  {
    "Name": "Gültekin BİBAR",
    "Birth Information": "ELAZIĞ - 1975",
    "Organization": "FETÖ/PDY Terör Örgütü",
    "Photo URL": "\"/kurumlar/terorarananlar.pol.tr/31KOMISYON/GULTEKIN-BIBAR.jpg\""
  },
  {
    "Name": "Emine TÜM",
    "Birth Information": "YUKARIBORANDERE KÖYÜ - 1975",
    "Organization": "PKK/KCK Terör Örgütü",
    "Photo URL": "\"/kurumlar/terorarananlar.pol.tr/Arsiv/1602/FotoOrj.jpeg\""
  },
  {
    "Name": "Hüseyin GEDİK",
    "Birth Information": "İSABEY - 1963",
    "Organization": "PKK/KCK Terör Örgütü",
    "Photo URL": "\"/kurumlar/terorarananlar.pol.tr/30-KOMISYON/22-HUSEYIN-GEDIK.jpg\""
  },
  {
    "Name": "Özlem ALPARSLAN",
    "Birth Information": "TUNCELİ - 1974",
    "Organization": "PKK/KCK Terör Örgütü",
    "Photo URL": "\"/kurumlar/terorarananlar.pol.tr/OZLEM-ALPARSLAN.jpg\""
  },
  {
    "Name": "Hasan MAHMUDİ",
    "Birth Information": "ERDABİL - 1977",
    "Organization": "PKK/KCK Terör Örgütü",
    "Photo URL": "\"/kurumlar/terorarananlar.pol.tr/HASAN-MAHMUDI.png\""
  },
  {
    "Name": "Lokman YALMAN",
    "Birth Information": "İDİL - 1969",
    "Organization": "PKK/KCK Terör Örgütü",
    "Photo URL": "\"/kurumlar/terorarananlar.pol.tr/31KOMISYON/LOKMAN-YALMAN.jpg\""
  },
  {
    "Name": "Ayten ENE",
    "Birth Information": "SIIRT - 1977",
    "Organization": "PKK/KCK Terör Örgütü",
    "Photo URL": "\"/kurumlar/terorarananlar.pol.tr/Ayten-ENE.png\""
  },
  {
    "Name": "Seyithan BAYDAR",
    "Birth Information": "GEVAŞ - 1988",
    "Organization": "PKK/KCK Terör Örgütü",
    "Photo URL": "\"/kurumlar/terorarananlar.pol.tr/36_KOMISYON/SEYITHAN-BAYDAR.jpg\""
  },
  {
    "Name": "Ali BORA",
    "Birth Information": "OSMANGAZI - 1995",
    "Organization": "DEAŞ Terör Örgütü",
    "Photo URL": "\"/kurumlar/terorarananlar.pol.tr/Arsiv/1622/FotoOrj.jpeg\""
  },
  {
    "Name": "Sinem EKİNCİ",
    "Birth Information": "PERTEK - 1989",
    "Organization": "PKK/KCK Terör Örgütü",
    "Photo URL": "\"/kurumlar/terorarananlar.pol.tr/SINEM-EKINCI.jpg\""
  },
  {
    "Name": "Abdullah YETİK",
    "Birth Information": "ÇORUM - 1980",
    "Organization": "FETÖ/PDY Terör Örgütü",
    "Photo URL": "\"/kurumlar/terorarananlar.pol.tr/Arsiv/1483/FotoOrj.jpeg\""
  },
  {
    "Name": "Nülüfer BORULDAY",
    "Birth Information": "ELAZIG - 1971",
    "Organization": "PKK/KCK Terör Örgütü",
    "Photo URL": "\"/kurumlar/terorarananlar.pol.tr/Arsiv/176/FotoOrj_1.jpeg\""
  },
  {
    "Name": "Bayram ALTUN",
    "Birth Information": "NUSAYBİN - 1974",
    "Organization": "PKK/KCK Terör Örgütü",
    "Photo URL": "\"/kurumlar/terorarananlar.pol.tr/30-KOMISYON/21-BAYRAM-ALTUN.jpg\""
  },
  {
    "Name": "Fehriye ERDAL",
    "Birth Information": "ADANA - 1977",
    "Organization": "DHKP/C Terör Örgütü",
    "Photo URL": "\"/kurumlar/terorarananlar.pol.tr/Arsiv/167/FotoOrj.jpeg\""
  },
  {
    "Name": "Burkay KARATEPE",
    "Birth Information": "EMIRDAG - 1984",
    "Organization": "FETÖ/PDY Terör Örgütü",
    "Photo URL": "\"/kurumlar/terorarananlar.pol.tr/Arsiv/1491/FotoOrj.jpeg\""
  },
  {
    "Name": "Gülşen AKSOY",
    "Birth Information": "GÖLYAZI - 1978",
    "Organization": "PKK/KCK Terör Örgütü",
    "Photo URL": "\"/kurumlar/terorarananlar.pol.tr/Arsiv/1570/FotoOrj.jpeg\""
  },
  {
    "Name": "Ridvan KIZILTEPE",
    "Birth Information": "İZMİR - 1954",
    "Organization": "FETÖ/PDY Terör Örgütü",
    "Photo URL": "\"/kurumlar/terorarananlar.pol.tr/31KOMISYON/RIDVAN-KIZILTEPE.jpg\""
  },
  {
    "Name": "Burak HAZAR",
    "Birth Information": "SEYHAN - 1992",
    "Organization": "DEAŞ Terör Örgütü",
    "Photo URL": "\"/kurumlar/terorarananlar.pol.tr/Arsiv/1497/FotoOrj.jpeg\""
  },
  {
    "Name": "Hülya ORAN",
    "Birth Information": "HOZAT - 1978",
    "Organization": "PKK/KCK Terör Örgütü",
    "Photo URL": "\"/kurumlar/terorarananlar.pol.tr/Arsiv/4/FotoOrj.jpeg\""
  },
  {
    "Name": "Ayşe DAYAN",
    "Birth Information": "ERUH - 1979",
    "Organization": "PKK/KCK Terör Örgütü",
    "Photo URL": "\"/kurumlar/terorarananlar.pol.tr/28-KOMISYON/21_AYSE-DAYAN.jpg\""
  },
  {
    "Name": "Nezete AKYÜZ",
    "Birth Information": "MİDYAT - 1979",
    "Organization": "PKK/KCK Terör Örgütü",
    "Photo URL": "\"/kurumlar/terorarananlar.pol.tr/28-KOMISYON/11_NEZETE-AKYUZ.jpg\""
  },
  {
    "Name": "Rıza PEKTAŞ",
    "Birth Information": "FETHIYE - 1968",
    "Organization": "TKP-ML Konferans Terör Örgütü",
    "Photo URL": "\"/kurumlar/terorarananlar.pol.tr/Arsiv/96/FotoOrj_1.jpeg\""
  },
  {
    "Name": "Ramazan MORKOÇ",
    "Birth Information": "ARDAHAN - 1967",
    "Organization": "PKK/KCK Terör Örgütü",
    "Photo URL": "\"/kurumlar/terorarananlar.pol.tr/31KOMISYON/RAMAZAN-MORKOC.jpg\""
  },
  {
    "Name": "Saban BOZAN",
    "Birth Information": "ÇUKURCA - 1968",
    "Organization": "PKK/KCK Terör Örgütü",
    "Photo URL": "\"/kurumlar/terorarananlar.pol.tr/Arsiv/300/FotoOrj.jpeg\""
  },
  {
    "Name": "Kemal KAYAR",
    "Birth Information": "DÜGER - 1961",
    "Organization": "DHKP/C Terör Örgütü",
    "Photo URL": "\"/kurumlar/terorarananlar.pol.tr/Arsiv/369/FotoOrj.jpeg\""
  },
  {
    "Name": "Filiz DEMİRCİ",
    "Birth Information": "BİNGÖL - 1987",
    "Organization": "PKK/KCK Terör Örgütü",
    "Photo URL": "\"/kurumlar/terorarananlar.pol.tr/30-KOMISYON/50-FILIZ-DEMIRCI.jpg\""
  },
  {
    "Name": "Bedran ÇAGLI",
    "Birth Information": "HİZAN - 1999",
    "Organization": "PKK/KCK Terör Örgütü",
    "Photo URL": "\"/kurumlar/terorarananlar.pol.tr/31KOMISYON/264-BEDRAN-CAGLI.jpg\""
  },
  {
    "Name": "Neşe BALTAŞ",
    "Birth Information": "MALAZGİRT - 1973",
    "Organization": "PKK/KCK Terör Örgütü",
    "Photo URL": "\"/kurumlar/terorarananlar.pol.tr/Arsiv/60/FotoOrj.jpeg\""
  },
  {
    "Name": "Ayfer KORDU",
    "Birth Information": "ÇAYIRLI - 1968",
    "Organization": "PKK/KCK Terör Örgütü",
    "Photo URL": "\"/kurumlar/terorarananlar.pol.tr/Arsiv/20/FotoOrj.jpeg\""
  },
  {
    "Name": "Mohammed Yousef Shaker DAHLAN",
    "Birth Information": "HAN YUNUS - 1961",
    "Organization": "FETÖ/PDY Terör Örgütü",
    "Photo URL": "\"/kurumlar/terorarananlar.pol.tr/Arsiv/1810/FotoOrj.jpeg\""
  },
  {
    "Name": "Dündar ALPARSLAN",
    "Birth Information": "ÖZALP - 1960",
    "Organization": "PKK/KCK Terör Örgütü",
    "Photo URL": "\"/kurumlar/terorarananlar.pol.tr/30-KOMISYON/20-DUNDAR-ALPARSLAN.jpg\""
  },
  {
    "Name": "Şemsettin SUYU",
    "Birth Information": "AHLAT - 1974",
    "Organization": "PKK/KCK Terör Örgütü",
    "Photo URL": "\"/kurumlar/terorarananlar.pol.tr/Arsiv/1051/FotoOrj.jpeg\""
  },
  {
    "Name": "Mehmet Kasim KARAY",
    "Birth Information": "YÜKSEKOVA - 1983",
    "Organization": "PKK/KCK Terör Örgütü",
    "Photo URL": "\"/kurumlar/terorarananlar.pol.tr/Arsiv/68/FotoOrj_1.jpeg\""
  },
  {
    "Name": "Cumhur Sinan OKTULMUŞ",
    "Birth Information": "TARSUS - 1983",
    "Organization": "TKP-ML Konferans Terör Örgütü",
    "Photo URL": "\"/kurumlar/terorarananlar.pol.tr/Arsiv/380/FotoOrj.jpeg\""
  },
  {
    "Name": "Memet Emin TOPRAK",
    "Birth Information": "DİYARBAKIR - 1972",
    "Organization": "PKK/KCK Terör Örgütü",
    "Photo URL": "\"/kurumlar/terorarananlar.pol.tr/30-KOMISYON/3_MEHMET-EMIN-TOPRAK.jpg\""
  },
  {
    "Name": "Bengin BİYAM",
    "Birth Information": "ERUH - 1972",
    "Organization": "PKK/KCK Terör Örgütü",
    "Photo URL": "\"/kurumlar/terorarananlar.pol.tr/Bengin-BIYAM.png\""
  },
  {
    "Name": "Mustafa YEŞİL",
    "Birth Information": "BIGA - 1963",
    "Organization": "FETÖ/PDY Terör Örgütü",
    "Photo URL": "\"/kurumlar/terorarananlar.pol.tr/Arsiv/249/FotoOrj.jpeg\""
  },
  {
    "Name": "Leyla GELİR",
    "Birth Information": "DEREİÇİ - 1976",
    "Organization": "PKK/KCK Terör Örgütü",
    "Photo URL": "\"/kurumlar/terorarananlar.pol.tr/30-KOMISYON/30-LEYLA-GELIR.jpg\""
  },
  {
    "Name": "Leman ŞİMŞEK",
    "Birth Information": "KONAK - 1989",
    "Organization": "PKK/KCK Terör Örgütü",
    "Photo URL": "\"/kurumlar/terorarananlar.pol.tr/28-KOMISYON/27_LEMAN-SIMSEK.jpg\""
  },
  {
    "Name": "Abdülkerim ARSLAN",
    "Birth Information": "ERCIS - 1979",
    "Organization": "PKK/KCK Terör Örgütü",
    "Photo URL": "\"/kurumlar/terorarananlar.pol.tr/Arsiv/1634/FotoOrj.jpeg\""
  }
]